[{"provider":"unknown","domain":"","bfs":"DO-001","name":"Altamira","district":"","country":"DO","canton":"Puerto Plata Province","osm_relation_id":7380617,"population":18868,"has_mx":false,"reason":"No MX records found"},{"provider":"unknown","domain":"","bfs":"DO-002","name":"Arenoso","district":"","country":"DO","canton":"Duarte Province","osm_relation_id":7376870,"population":14062,"has_mx":false,"reason":"No MX records found"},{"provider":"unknown","domain":"","bfs":"DO-003","name":"Azua","district":"","country":"DO","canton":"Azua Province","population":103276,"has_mx":false,"reason":"No MX records found"},{"provider":"unknown","domain":"","bfs":"DO-004","name":"Baitoa","district":"","country":"DO","canton":"Santiago Province","population":11,"has_mx":false,"reason":"No MX records found"},{"provider":"unknown","domain":"","bfs":"DO-005","name":"Bajos de Haina","district":"","country":"DO","canton":"San Cristóbal Province","osm_relation_id":7159796,"population":155985,"has_mx":false,"reason":"No MX records found"},{"provider":"unknown","domain":"","bfs":"DO-006","name":"Baní","district":"","country":"DO","canton":"Peravia Province","osm_relation_id":7394782,"population":157316,"has_mx":false,"reason":"No MX records found"},{"provider":"unknown","domain":"","bfs":"DO-007","name":"Bayaguana","district":"","country":"DO","canton":"Monte Plata Province","osm_relation_id":7405667,"population":31889,"has_mx":false,"reason":"No MX records found"},{"provider":"google","domain":"bisono.do","bfs":"DO-008","name":"Bisonó","district":"","mx_countries":["US"],"country":"DO","canton":"Santiago Province","osm_relation_id":7380647,"population":42092,"has_mx":true,"mx":["alt1.aspmx.l.google.com","alt2.aspmx.l.google.com","alt3.aspmx.l.google.com","alt4.aspmx.l.google.com","aspmx.l.google.com"],"reason":"MX record (alt1.aspmx.l.google.com, alt2.aspmx.l.google.com) matches Google","spf":"v=spf1 include:_spf.google.com -all","txt_verifications":{"google":"SreoJkIj8ibtNccQpjyeiEbtMaV-7lP-9gWEsEvHtoY"}},{"provider":"unknown","domain":"","bfs":"DO-009","name":"Boca Chica","district":"","country":"DO","canton":"Santo Domingo Province","osm_relation_id":7407701,"population":142019,"has_mx":false,"reason":"No MX records found"},{"provider":"google","domain":"bohechiodigital.com","bfs":"DO-010","name":"Bohechío","district":"","mx_countries":["US"],"country":"DO","canton":"San Juan Province","osm_relation_id":7155987,"population":9685,"has_mx":true,"mx":["alt1.aspmx.l.google.com","alt2.aspmx.l.google.com","aspmx.l.google.com","aspmx2.googlemail.com","aspmx3.googlemail.com","aspmx4.googlemail.com","aspmx5.googlemail.com"],"reason":"MX record (alt1.aspmx.l.google.com, alt2.aspmx.l.google.com) matches Google"},{"provider":"unknown","domain":"","bfs":"DO-011","name":"Bonao","district":"","country":"DO","canton":"Monseñor Nouel Province","osm_relation_id":7384719,"population":158034,"has_mx":false,"reason":"No MX records found"},{"provider":"unknown","domain":"","bfs":"DO-012","name":"Bánica","district":"","country":"DO","canton":"Elías Piña Province","osm_relation_id":7400827,"population":6533,"has_mx":false,"reason":"No MX records found"},{"provider":"google","domain":"cabral.do","bfs":"DO-013","name":"Cabral","district":"","mx_countries":["US"],"country":"DO","canton":"Barahona Province","osm_relation_id":7149200,"population":14823,"has_mx":true,"mx":["alt1.aspmx.l.google.com","alt2.aspmx.l.google.com","alt3.aspmx.l.google.com","alt4.aspmx.l.google.com","aspmx.l.google.com"],"reason":"MX record (alt1.aspmx.l.google.com, alt2.aspmx.l.google.com) matches Google","spf":"v=spf1 include:_spf.google.com -all","txt_verifications":{"google":"bjM43FBZJ-iUrQ_hdnryqWLPq3-MH1U7oDCQK9kiH7U"}},{"provider":"unknown","domain":"","bfs":"DO-014","name":"Cambita Garabitos","district":"","country":"DO","canton":"San Cristóbal Province","osm_relation_id":7394815,"population":31057,"has_mx":false,"reason":"No MX records found"},{"provider":"unknown","domain":"","bfs":"DO-015","name":"Castañuela","district":"","country":"DO","canton":"Monte Cristi Province","osm_relation_id":7187303,"population":14921,"has_mx":false,"reason":"No MX records found"},{"provider":"unknown","domain":"","bfs":"DO-016","name":"Castillo","district":"","country":"DO","canton":"Duarte Province","osm_relation_id":7386285,"population":15709,"has_mx":false,"reason":"No MX records found"},{"provider":"unknown","domain":"","bfs":"DO-017","name":"Cayetano Germosén","district":"","country":"DO","canton":"Espaillat Province","osm_relation_id":7366014,"population":6911,"has_mx":false,"reason":"No MX records found"},{"provider":"unknown","domain":"","bfs":"DO-018","name":"Cevicos. Alcalde","district":"","country":"DO","canton":"Sánchez Ramírez Province","osm_relation_id":7384706,"population":16311,"has_mx":false,"reason":"No MX records found"},{"provider":"unknown","domain":"","bfs":"DO-019","name":"Comendador","district":"","country":"DO","canton":"Elías Piña Province","osm_relation_id":7400760,"population":25924,"has_mx":false,"reason":"No MX records found"},{"provider":"unknown","domain":"alcaldiaconstanza.com","bfs":"DO-020","name":"Constanza","district":"","country":"DO","canton":"La Vega Province","population":59052,"has_mx":false,"reason":"No MX records found"},{"provider":"unknown","domain":"","bfs":"DO-021","name":"Cotuí","district":"","country":"DO","canton":"Sánchez Ramírez Province","population":76554,"has_mx":false,"reason":"No MX records found"},{"provider":"unknown","domain":"","bfs":"DO-022","name":"Cristóbal","district":"","country":"DO","canton":"Independencia","osm_relation_id":7153746,"population":7617,"has_mx":false,"reason":"No MX records found"},{"provider":"unknown","domain":"","bfs":"DO-023","name":"Dajabón","district":"","country":"DO","canton":"Dajabón Province","population":28071,"has_mx":false,"reason":"No MX records found"},{"provider":"unknown","domain":"","bfs":"DO-024","name":"Duvergé","district":"","country":"DO","canton":"Independencia","osm_relation_id":7153735,"population":12029,"has_mx":false,"reason":"No MX records found"},{"provider":"unknown","domain":"","bfs":"DO-025","name":"El Cercado","district":"","country":"DO","canton":"San Juan Province","osm_relation_id":7155990,"population":20843,"has_mx":false,"reason":"No MX records found"},{"provider":"unknown","domain":"","bfs":"DO-026","name":"El Factor","district":"","country":"DO","canton":"María Trinidad Sánchez Province","osm_relation_id":7386633,"population":29736,"has_mx":false,"reason":"No MX records found"},{"provider":"unknown","domain":"","bfs":"DO-027","name":"El Llano","district":"","country":"DO","canton":"Elías Piña Province","osm_relation_id":7155959,"population":8344,"has_mx":false,"reason":"No MX records found"},{"provider":"unknown","domain":"","bfs":"DO-028","name":"El Peñón","district":"","country":"DO","canton":"Barahona Province","osm_relation_id":7151618,"population":3970,"has_mx":false,"reason":"No MX records found"},{"provider":"unknown","domain":"","bfs":"DO-029","name":"El Pino","district":"","country":"DO","canton":"Dajabón Province","osm_relation_id":7187302,"population":6035,"has_mx":false,"reason":"No MX records found"},{"provider":"unknown","domain":"","bfs":"DO-030","name":"El Valle","district":"","country":"DO","canton":"Hato Mayor Province","population":7228,"has_mx":false,"reason":"No MX records found"},{"provider":"unknown","domain":"","bfs":"DO-031","name":"Enriquillo","district":"","country":"DO","canton":"Barahona Province","population":12523,"has_mx":false,"reason":"No MX records found"},{"provider":"unknown","domain":"","bfs":"DO-032","name":"Esperanza","district":"","country":"DO","canton":"Valverde Province","osm_relation_id":7391016,"population":62205,"has_mx":false,"reason":"No MX records found"},{"provider":"unknown","domain":"","bfs":"DO-033","name":"Estebanía","district":"","country":"DO","canton":"Azua Province","osm_relation_id":7394777,"population":8227,"has_mx":false,"reason":"No MX records found"},{"provider":"unknown","domain":"","bfs":"DO-034","name":"Fantino","district":"","country":"DO","canton":"Sánchez Ramírez Province","osm_relation_id":7384712,"population":23780,"has_mx":false,"reason":"No MX records found"},{"provider":"unknown","domain":"","bfs":"DO-035","name":"Fundación","district":"","country":"DO","canton":"Barahona Province","osm_relation_id":7151620,"population":9223,"has_mx":false,"reason":"No MX records found"},{"provider":"unknown","domain":"","bfs":"DO-036","name":"Galván","district":"","country":"DO","canton":"Baoruco Province","osm_relation_id":7151393,"population":15702,"has_mx":false,"reason":"No MX records found"},{"provider":"unknown","domain":"","bfs":"DO-037","name":"Gaspar Hernández","district":"","country":"DO","canton":"Espaillat Province","osm_relation_id":7366018,"population":37378,"has_mx":false,"reason":"No MX records found"},{"provider":"unknown","domain":"","bfs":"DO-038","name":"Guananico","district":"","country":"DO","canton":"Puerto Plata Province","osm_relation_id":7366332,"population":8950,"has_mx":false,"reason":"No MX records found"},{"provider":"unknown","domain":"","bfs":"DO-039","name":"Guayabal","district":"","country":"DO","canton":"Azua Province","osm_relation_id":7394770,"population":5263,"has_mx":false,"reason":"No MX records found"},{"provider":"unknown","domain":"","bfs":"DO-040","name":"Guayacanes","district":"","country":"DO","canton":"San Pedro de Macorís","osm_relation_id":7405613,"population":14592,"has_mx":false,"reason":"No MX records found"},{"provider":"unknown","domain":"","bfs":"DO-041","name":"Guaymate","district":"","country":"DO","canton":"La Romana","osm_relation_id":7405535,"population":17228,"has_mx":false,"reason":"No MX records found"},{"provider":"unknown","domain":"","bfs":"DO-042","name":"Guayubín","district":"","country":"DO","canton":"Monte Cristi Province","osm_relation_id":7390982,"population":35923,"has_mx":false,"reason":"No MX records found"},{"provider":"unknown","domain":"","bfs":"DO-043","name":"Hato Mayor del Rey","district":"","country":"DO","canton":"Hato Mayor Province","population":61517,"has_mx":false,"reason":"No MX records found"},{"provider":"independent","domain":"higuey.info","bfs":"DO-044","name":"Higüey","district":"","mx_countries":["US"],"country":"DO","canton":"La Altagracia Province","population":251243,"has_mx":true,"mx":["higuey.info"],"reason":"MX (higuey.info) is self-hosted","spf":"v=spf1 +a +mx +ip4:66.225.221.194 ~all","autodiscover":{"autodiscover_srv":"cpanelemaildiscovery.cpanel.net"}},{"provider":"unknown","domain":"","bfs":"DO-045","name":"Hondo Valle","district":"","country":"DO","canton":"Elías Piña Province","osm_relation_id":7155960,"population":10587,"has_mx":false,"reason":"No MX records found"},{"provider":"unknown","domain":"","bfs":"DO-046","name":"Hostos","district":"","country":"DO","canton":"Duarte Province","population":5497,"has_mx":false,"reason":"No MX records found"},{"provider":"unknown","domain":"","bfs":"DO-047","name":"Imbert","district":"","country":"DO","canton":"Puerto Plata Province","osm_relation_id":7366345,"population":22058,"has_mx":false,"reason":"No MX records found"},{"provider":"unknown","domain":"","bfs":"DO-048","name":"Jamao al Norte","district":"","country":"DO","canton":"Espaillat Province","osm_relation_id":7366308,"population":7820,"has_mx":false,"reason":"No MX records found"},{"provider":"unknown","domain":"","bfs":"DO-049","name":"Jaquimeyes","district":"","country":"DO","canton":"Barahona Province","osm_relation_id":7400753,"population":4491,"has_mx":false,"reason":"No MX records found"},{"provider":"unknown","domain":"","bfs":"DO-050","name":"Jarabacoa","district":"","country":"DO","canton":"La Vega Province","population":58803,"has_mx":false,"reason":"No MX records found"},{"provider":"google","domain":"jaragua.do","bfs":"DO-051","name":"Jaragua","district":"","mx_countries":["US"],"country":"DO","canton":"Baoruco Province","osm_relation_id":7151459,"population":10619,"has_mx":true,"mx":["alt1.aspmx.l.google.com","alt2.aspmx.l.google.com","alt3.aspmx.l.google.com","alt4.aspmx.l.google.com","aspmx.l.google.com"],"reason":"MX record (alt1.aspmx.l.google.com, alt2.aspmx.l.google.com) matches Google","spf":"v=spf1 include:_spf.google.com ~all","txt_verifications":{"google":"TCuPZCDZJdd_wvj8dAQyiUcFZ0W9wEciwCTaOiqH4Ww"}},{"provider":"unknown","domain":"","bfs":"DO-052","name":"Jima Abajo","district":"","country":"DO","canton":"La Vega Province","osm_relation_id":7373852,"population":30261,"has_mx":false,"reason":"No MX records found"},{"provider":"unknown","domain":"","bfs":"DO-053","name":"Jimaní","district":"","country":"DO","canton":"Independencia","osm_relation_id":7153734,"population":16510,"has_mx":false,"reason":"No MX records found"},{"provider":"unknown","domain":"","bfs":"DO-054","name":"Juan Santiago","district":"","country":"DO","canton":"Elías Piña Province","osm_relation_id":7155984,"population":4360,"has_mx":false,"reason":"No MX records found"},{"provider":"unknown","domain":"","bfs":"DO-055","name":"Juan de Herrera","district":"","country":"DO","canton":"San Juan Province","osm_relation_id":7400853,"population":13062,"has_mx":false,"reason":"No MX records found"},{"provider":"unknown","domain":"","bfs":"DO-056","name":"Jánico","district":"","country":"DO","canton":"Santiago Province","osm_relation_id":7380651,"population":16993,"has_mx":false,"reason":"No MX records found"},{"provider":"unknown","domain":"","bfs":"DO-057","name":"La Ciénaga","district":"","country":"DO","canton":"Barahona Province","osm_relation_id":7151619,"population":9112,"has_mx":false,"reason":"No MX records found"},{"provider":"unknown","domain":"","bfs":"DO-058","name":"La Descubierta","district":"","country":"DO","canton":"Independencia","osm_relation_id":7153737,"population":8310,"has_mx":false,"reason":"No MX records found"},{"provider":"unknown","domain":"","bfs":"DO-059","name":"La Mata","district":"","country":"DO","canton":"Sánchez Ramírez Province","osm_relation_id":7384718,"population":38962,"has_mx":false,"reason":"No MX records found"},{"provider":"unknown","domain":"","bfs":"DO-060","name":"La Romana","district":"","country":"DO","canton":"La Romana","osm_relation_id":7405532,"population":139238,"has_mx":false,"reason":"No MX records found"},{"provider":"independent","domain":"lavega.com","bfs":"DO-061","name":"La Vega","district":"","country":"DO","canton":"La Vega Province","population":220279,"has_mx":true,"mx":["_dc-mx.53f489fd2075.lavega.com"],"reason":"MX (_dc-mx.53f489fd2075.lavega.com) is self-hosted","spf":"v=spf1 +a +mx +ip4:162.254.145.222 ~all","txt_verifications":{"google":"apnwH_lDEPw1M6e7ZjlGn6MEXe4N6G7cXFqDklHzuTY"}},{"provider":"unknown","domain":"","bfs":"DO-062","name":"Laguna Salada","district":"","country":"DO","canton":"Valverde Province","osm_relation_id":7391022,"population":23962,"has_mx":false,"reason":"No MX records found"},{"provider":"unknown","domain":"","bfs":"DO-063","name":"Las Charcas","district":"","country":"DO","canton":"Azua Province","osm_relation_id":7162901,"population":14341,"has_mx":false,"reason":"No MX records found"},{"provider":"independent","domain":"lasguaranas.org","bfs":"DO-064","name":"Las Guáranas","district":"","mx_countries":["US"],"country":"DO","canton":"Duarte Province","osm_relation_id":7386390,"population":14661,"has_mx":true,"mx":["mx1.hostinger.com","mx2.hostinger.com"],"reason":"MX (mx1.hostinger.com, mx2.hostinger.com) is self-hosted","spf":"v=spf1 include:_spf.mail.hostinger.com ~all","autodiscover":{"autodiscover_cname":"autodiscover.mail.hostinger.com"}},{"provider":"unknown","domain":"","bfs":"DO-065","name":"Las Matas de Farfán","district":"","country":"DO","canton":"San Juan Province","osm_relation_id":7400868,"population":44163,"has_mx":false,"reason":"No MX records found"},{"provider":"unknown","domain":"","bfs":"DO-066","name":"Las Matas de Santa Cruz","district":"","country":"DO","canton":"Monte Cristi Province","osm_relation_id":7187306,"population":11114,"has_mx":false,"reason":"No MX records found"},{"provider":"unknown","domain":"","bfs":"DO-067","name":"Las Salinas","district":"","country":"DO","canton":"Barahona Province","osm_relation_id":7151622,"population":4703,"has_mx":false,"reason":"No MX records found"},{"provider":"unknown","domain":"","bfs":"DO-068","name":"Las Terrenas","district":"","country":"DO","canton":"Samaná Province","osm_relation_id":7187336,"population":18829,"has_mx":false,"reason":"No MX records found"},{"provider":"unknown","domain":"lasyayas.com.do","bfs":"DO-069","name":"Las Yayas de Viajama","district":"","country":"DO","canton":"Azua Province","osm_relation_id":7394727,"population":17620,"has_mx":false,"reason":"No MX records found"},{"provider":"unknown","domain":"","bfs":"DO-070","name":"Licey al Medio","district":"","country":"DO","canton":"Santiago Province","osm_relation_id":7380690,"population":25539,"has_mx":false,"reason":"No MX records found"},{"provider":"unknown","domain":"","bfs":"DO-071","name":"Loma de Cabrera","district":"","country":"DO","canton":"Dajabón Province","osm_relation_id":7390913,"population":15624,"has_mx":false,"reason":"No MX records found"},{"provider":"unknown","domain":"","bfs":"DO-072","name":"Los Alcarrizos","district":"","country":"DO","canton":"Santo Domingo Province","osm_relation_id":7407715,"population":272776,"has_mx":false,"reason":"No MX records found"},{"provider":"unknown","domain":"","bfs":"DO-073","name":"Los Cacaos","district":"","country":"DO","canton":"San Cristóbal Province","osm_relation_id":7394816,"population":13778,"has_mx":false,"reason":"No MX records found"},{"provider":"unknown","domain":"","bfs":"DO-074","name":"Los Hidalgos","district":"","country":"DO","canton":"Puerto Plata Province","osm_relation_id":7366401,"population":12639,"has_mx":false,"reason":"No MX records found"},{"provider":"unknown","domain":"","bfs":"DO-075","name":"Los Ríos","district":"","country":"DO","canton":"Baoruco Province","osm_relation_id":7151462,"population":9305,"has_mx":false,"reason":"No MX records found"},{"provider":"unknown","domain":"","bfs":"DO-076","name":"Luperón","district":"","country":"DO","canton":"Puerto Plata Province","osm_relation_id":7380629,"population":20259,"has_mx":false,"reason":"No MX records found"},{"provider":"unknown","domain":"","bfs":"DO-077","name":"Maimón","district":"","country":"DO","canton":"Monseñor Nouel Province","osm_relation_id":7384722,"population":23885,"has_mx":false,"reason":"No MX records found"},{"provider":"unknown","domain":"","bfs":"DO-078","name":"Mao","district":"","country":"DO","canton":"Valverde Province","population":76863,"has_mx":false,"reason":"No MX records found"},{"provider":"unknown","domain":"","bfs":"DO-079","name":"Matanzas, Prov. Peravia, Rep. Dom","district":"","country":"DO","canton":"Peravia Province","population":19162,"has_mx":false,"reason":"No MX records found"},{"provider":"microsoft","domain":"mella.do","bfs":"DO-080","name":"Mella","district":"","mx_countries":["US"],"country":"DO","canton":"Independencia","osm_relation_id":7153747,"population":3641,"has_mx":true,"mx":["mella-do.mail.protection.outlook.com"],"reason":"MX record (mella-do.mail.protection.outlook.com) matches Microsoft","spf":"v=spf1 include:spf.protection.outlook.com -all","autodiscover":{"autodiscover_cname":"autodiscover.outlook.com"}},{"provider":"unknown","domain":"","bfs":"DO-081","name":"Miches","district":"","country":"DO","canton":"El Seibo Province","osm_relation_id":7400887,"population":20813,"has_mx":false,"reason":"No MX records found"},{"provider":"unknown","domain":"ayuntamientomoca.gob.do","bfs":"DO-082","name":"Moca","district":"","country":"DO","canton":"Espaillat Province","population":94981,"has_mx":false,"reason":"No MX records found"},{"provider":"unknown","domain":"","bfs":"DO-083","name":"Monción","district":"","country":"DO","canton":"Santiago Rodríguez Province","osm_relation_id":7391002,"population":11753,"has_mx":false,"reason":"No MX records found"},{"provider":"unknown","domain":"","bfs":"DO-084","name":"Monte Cristi","district":"","country":"DO","canton":"Monte Cristi Province","osm_relation_id":7390957,"population":25776,"has_mx":false,"reason":"No MX records found"},{"provider":"unknown","domain":"","bfs":"DO-085","name":"Monte Plata","district":"","country":"DO","canton":"Monte Plata Province","population":37614,"has_mx":false,"reason":"No MX records found"},{"provider":"unknown","domain":"","bfs":"DO-086","name":"Municipio Consuelo","district":"","country":"DO","canton":"San Pedro de Macorís","osm_relation_id":7158789,"population":30051,"has_mx":false,"reason":"No MX records found"},{"provider":"unknown","domain":"","bfs":"DO-087","name":"Municipio de Cabrera","district":"","country":"DO","canton":"María Trinidad Sánchez Province","osm_relation_id":7187309,"population":25524,"has_mx":false,"reason":"No MX records found"},{"provider":"unknown","domain":"","bfs":"DO-088","name":"Nagua","district":"","country":"DO","canton":"María Trinidad Sánchez Province","population":76933,"has_mx":false,"reason":"No MX records found"},{"provider":"unknown","domain":"","bfs":"DO-089","name":"Neiba","district":"","country":"DO","canton":"Baoruco Province","osm_relation_id":7156012,"population":36511,"has_mx":false,"reason":"No MX records found"},{"provider":"unknown","domain":"","bfs":"DO-090","name":"Nizao","district":"","country":"DO","canton":"Peravia Province","osm_relation_id":7394787,"population":27028,"has_mx":false,"reason":"No MX records found"},{"provider":"unknown","domain":"","bfs":"DO-091","name":"Oviedo","district":"","country":"DO","canton":"Pedernales Province","osm_relation_id":7153752,"population":7296,"has_mx":false,"reason":"No MX records found"},{"provider":"unknown","domain":"","bfs":"DO-092","name":"Padre Las Casas","district":"","country":"DO","canton":"Azua Province","osm_relation_id":7394737,"population":20041,"has_mx":false,"reason":"No MX records found"},{"provider":"unknown","domain":"","bfs":"DO-093","name":"Paraíso","district":"","country":"DO","canton":"Barahona Province","osm_relation_id":7394881,"population":15390,"has_mx":false,"reason":"No MX records found"},{"provider":"unknown","domain":"","bfs":"DO-094","name":"Partido","district":"","country":"DO","canton":"Dajabón Province","osm_relation_id":7390919,"population":6951,"has_mx":false,"reason":"No MX records found"},{"provider":"unknown","domain":"","bfs":"DO-095","name":"Pedernales","district":"","country":"DO","canton":"Pedernales Province","osm_relation_id":7153751,"population":24291,"has_mx":false,"reason":"No MX records found"},{"provider":"unknown","domain":"","bfs":"DO-096","name":"Pedro Brand","district":"","country":"DO","canton":"Santo Domingo Province","osm_relation_id":7407721,"population":74016,"has_mx":false,"reason":"No MX records found"},{"provider":"unknown","domain":"","bfs":"DO-097","name":"Pedro Santana","district":"","country":"DO","canton":"Elías Piña Province","osm_relation_id":7400837,"population":7281,"has_mx":false,"reason":"No MX records found"},{"provider":"unknown","domain":"","bfs":"DO-098","name":"Pepillo Salcedo","district":"","country":"DO","canton":"Monte Cristi Province","osm_relation_id":7167287,"population":9136,"has_mx":false,"reason":"No MX records found"},{"provider":"unknown","domain":"","bfs":"DO-099","name":"Peralta","district":"","country":"DO","canton":"Azua Province","osm_relation_id":7394756,"population":15257,"has_mx":false,"reason":"No MX records found"},{"provider":"unknown","domain":"","bfs":"DO-100","name":"Peralvillo","district":"","country":"DO","canton":"Monte Plata Province","osm_relation_id":7158797,"population":20900,"has_mx":false,"reason":"No MX records found"},{"provider":"unknown","domain":"","bfs":"DO-101","name":"Piedra Blanca","district":"","country":"DO","canton":"Monseñor Nouel Province","osm_relation_id":7373854,"population":30511,"has_mx":false,"reason":"No MX records found"},{"provider":"independent","domain":"pimentel.do","bfs":"DO-102","name":"Pimentel","district":"","mx_countries":["US"],"country":"DO","canton":"Duarte Province","osm_relation_id":7386295,"population":17864,"has_mx":true,"mx":["mx.pimentel.do"],"reason":"MX (mx.pimentel.do) is self-hosted","spf":"v=spf1 ip4:66.96.128.0/18 include:websitewelcome.com ?all","txt_verifications":{"google":"0jzDrJJu5_W6eNs9zPAqUDnlf91DnPYgDO4OvMr9C1Y"}},{"provider":"unknown","domain":"","bfs":"DO-103","name":"Polo","district":"","country":"DO","canton":"Barahona Province","osm_relation_id":7400721,"population":8186,"has_mx":false,"reason":"No MX records found"},{"provider":"unknown","domain":"","bfs":"DO-104","name":"Postrer Río","district":"","country":"DO","canton":"Independencia","osm_relation_id":7153745,"population":7178,"has_mx":false,"reason":"No MX records found"},{"provider":"unknown","domain":"","bfs":"DO-105","name":"Pueblo Viejo","district":"","country":"DO","canton":"Azua Province","osm_relation_id":7162902,"population":11235,"has_mx":false,"reason":"No MX records found"},{"provider":"independent","domain":"puertoplata.com","bfs":"DO-106","name":"Puerto Plata","district":"","mx_countries":["US"],"country":"DO","canton":"Puerto Plata Province","osm_relation_id":7380607,"population":338339,"has_mx":true,"mx":["mx07.register.com"],"reason":"MX (mx07.register.com) is self-hosted","spf":"v=spf1 include:spf.registeredsite.com -all"},{"provider":"unknown","domain":"","bfs":"DO-107","name":"Puñal","district":"","country":"DO","canton":"Santiago Province","osm_relation_id":7380742,"population":46090,"has_mx":false,"reason":"No MX records found"},{"provider":"unknown","domain":"","bfs":"DO-108","name":"Ramón Santana","district":"","country":"DO","canton":"San Pedro de Macorís","osm_relation_id":7158788,"population":8901,"has_mx":false,"reason":"No MX records found"},{"provider":"unknown","domain":"","bfs":"DO-109","name":"Rancho Arriba","district":"","country":"DO","canton":"San José de Ocoa Province","osm_relation_id":7156019,"population":14052,"has_mx":false,"reason":"No MX records found"},{"provider":"unknown","domain":"","bfs":"DO-110","name":"Restauración","district":"","country":"DO","canton":"Dajabón Province","osm_relation_id":7390953,"population":7274,"has_mx":false,"reason":"No MX records found"},{"provider":"unknown","domain":"","bfs":"DO-111","name":"Río San Juan","district":"","country":"DO","canton":"María Trinidad Sánchez Province","osm_relation_id":7187312,"population":15168,"has_mx":false,"reason":"No MX records found"},{"provider":"unknown","domain":"","bfs":"DO-112","name":"Sabana Grande de Boyá","district":"","country":"DO","canton":"Monte Plata Province","osm_relation_id":7405672,"population":31096,"has_mx":false,"reason":"No MX records found"},{"provider":"unknown","domain":"","bfs":"DO-113","name":"Sabana Grande de Palenque","district":"","country":"DO","canton":"San Cristóbal Province","osm_relation_id":7159795,"population":15466,"has_mx":false,"reason":"No MX records found"},{"provider":"unknown","domain":"","bfs":"DO-114","name":"Sabana Iglesia","district":"","country":"DO","canton":"Santiago Province","osm_relation_id":7380752,"population":13348,"has_mx":false,"reason":"No MX records found"},{"provider":"unknown","domain":"","bfs":"DO-115","name":"Sabana Larga","district":"","country":"DO","canton":"San José de Ocoa Province","osm_relation_id":7394827,"population":11636,"has_mx":false,"reason":"No MX records found"},{"provider":"unknown","domain":"","bfs":"DO-116","name":"Sabana Yegua","district":"","country":"DO","canton":"Azua Province","population":11235,"has_mx":false,"reason":"No MX records found"},{"provider":"unknown","domain":"","bfs":"DO-117","name":"Sabana de la Mar","district":"","country":"DO","canton":"Hato Mayor Province","osm_relation_id":7407668,"population":16272,"has_mx":false,"reason":"No MX records found"},{"provider":"unknown","domain":"","bfs":"DO-118","name":"Sabaneta","district":"","country":"DO","canton":"Santiago Rodríguez Province","population":34540,"has_mx":false,"reason":"No MX records found"},{"provider":"unknown","domain":"","bfs":"DO-119","name":"Salcedo","district":"","country":"DO","canton":"Hermanas Mirabal Province","population":39557,"has_mx":false,"reason":"No MX records found"},{"provider":"unknown","domain":"","bfs":"DO-120","name":"Samaná","district":"","country":"DO","canton":"Samaná Province","osm_relation_id":7386746,"population":108179,"has_mx":false,"reason":"No MX records found"},{"provider":"unknown","domain":"","bfs":"DO-121","name":"San Antonio de Guerra","district":"","country":"DO","canton":"Santo Domingo Province","osm_relation_id":7376886,"population":43963,"has_mx":false,"reason":"No MX records found"},{"provider":"unknown","domain":"sancristobal.org.do","bfs":"DO-122","name":"San Cristóbal","district":"","country":"DO","canton":"San Cristóbal Province","osm_relation_id":7394810,"population":275232,"has_mx":false,"reason":"No MX records found"},{"provider":"unknown","domain":"sanfrancisco.gob.do","bfs":"DO-123","name":"San Francisco de Macorís","district":"","country":"DO","canton":"Duarte Province","population":188118,"has_mx":false,"reason":"No MX records found"},{"provider":"unknown","domain":"","bfs":"DO-124","name":"San Gregorio de Nigua","district":"","country":"DO","canton":"San Cristóbal Province","osm_relation_id":7159852,"population":40589,"has_mx":false,"reason":"No MX records found"},{"provider":"unknown","domain":"","bfs":"DO-125","name":"San José de Ocoa","district":"","country":"DO","canton":"San José de Ocoa Province","osm_relation_id":7394824,"population":57174,"has_mx":false,"reason":"No MX records found"},{"provider":"unknown","domain":"","bfs":"DO-126","name":"San José de las Matas","district":"","country":"DO","canton":"Santiago Province","osm_relation_id":7380701,"population":38628,"has_mx":false,"reason":"No MX records found"},{"provider":"unknown","domain":"","bfs":"DO-127","name":"San José de los Llanos","district":"","country":"DO","canton":"San Pedro de Macorís","osm_relation_id":7405604,"population":22573,"has_mx":false,"reason":"No MX records found"},{"provider":"unknown","domain":"","bfs":"DO-128","name":"San Juan de la Maguana","district":"","country":"DO","canton":"San Juan Province","population":132177,"has_mx":false,"reason":"No MX records found"},{"provider":"unknown","domain":"","bfs":"DO-129","name":"San Pedro de Macorís","district":"","country":"DO","canton":"San Pedro de Macorís","population":195307,"has_mx":false,"reason":"No MX records found"},{"provider":"unknown","domain":"","bfs":"DO-130","name":"San Rafael del Yuma","district":"","country":"DO","canton":"La Altagracia Province","osm_relation_id":7405521,"population":21967,"has_mx":false,"reason":"No MX records found"},{"provider":"unknown","domain":"","bfs":"DO-131","name":"San Victor","district":"","country":"DO","canton":"Espaillat Province","population":21009,"has_mx":false,"reason":"No MX records found"},{"provider":"unknown","domain":"","bfs":"DO-132","name":"Santa Cruz de Barahona","district":"","country":"DO","canton":"Barahona Province","population":83619,"has_mx":false,"reason":"No MX records found"},{"provider":"unknown","domain":"","bfs":"DO-133","name":"Santa Cruz del Seibo","district":"","country":"DO","canton":"El Seibo Province","population":66867,"has_mx":false,"reason":"No MX records found"},{"provider":"unknown","domain":"santiagodeloscaballeros.gob.do","bfs":"DO-134","name":"Santiago de los Caballeros","district":"","country":"DO","canton":"Santiago Province","population":1343423,"has_mx":false,"reason":"No MX records found"},{"provider":"microsoft","domain":"asde.gov.do","bfs":"DO-135","name":"Santo Domingo Este","district":"","mx_countries":["US"],"country":"DO","canton":"Santo Domingo Province","osm_relation_id":7407685,"population":948855,"has_mx":true,"mx":["asde-gov-do.mail.protection.outlook.com"],"reason":"MX record (asde-gov-do.mail.protection.outlook.com) matches Microsoft","spf":"v=spf1 include:spf.protection.outlook.com ~all","autodiscover":{"autodiscover_cname":"autodiscover.outlook.com"},"txt_verifications":{"microsoft":"ms25643313"}},{"provider":"unknown","domain":"ayuntamientosde.gob.do","bfs":"DO-136","name":"Santo Domingo Norte","district":"","country":"DO","canton":"Santo Domingo Province","osm_relation_id":7407691,"population":529390,"has_mx":false,"reason":"No MX records found"},{"provider":"unknown","domain":"asdo.gov.do","bfs":"DO-137","name":"Santo Domingo Oeste","district":"","country":"DO","canton":"Santo Domingo Province","osm_relation_id":7407687,"population":363321,"has_mx":false,"reason":"No MX records found"},{"provider":"google","domain":"thegoodlifesosua.com","bfs":"DO-138","name":"Sosúa","district":"","mx_countries":["US"],"country":"DO","canton":"Puerto Plata Province","osm_relation_id":7367027,"population":69885,"has_mx":true,"mx":["alt1.aspmx.l.google.com","alt2.aspmx.l.google.com","alt3.aspmx.l.google.com","alt4.aspmx.l.google.com","aspmx.l.google.com"],"reason":"MX record (alt1.aspmx.l.google.com, alt2.aspmx.l.google.com) matches Google","spf":"v=spf1 include:_spf.google.com include:_spf.wpcloud.com ~all","autodiscover":{"autodiscover_cname":"thegoodlifesosua.com"},"txt_verifications":{"google":"xEcqH2MKnp1b9jqHuZRQQ1adKJs2sGJzLVXr6Ei7aA8","facebook":"2fgzvh9obl6fk22ohexxzwkq3wooxe"}},{"provider":"google","domain":"sanchez.do","bfs":"DO-139","name":"Sánchez","district":"","mx_countries":["US"],"country":"DO","canton":"Samaná Province","osm_relation_id":7386768,"population":25000,"has_mx":true,"mx":["alt1.aspmx.l.google.com","alt2.aspmx.l.google.com","alt3.aspmx.l.google.com","alt4.aspmx.l.google.com","aspmx.l.google.com"],"reason":"MX record (alt1.aspmx.l.google.com, alt2.aspmx.l.google.com) matches Google"},{"provider":"unknown","domain":"","bfs":"DO-140","name":"Tabara Arriba","district":"","country":"DO","canton":"Azua Province","osm_relation_id":7394767,"population":17647,"has_mx":false,"reason":"No MX records found"},{"provider":"unknown","domain":"","bfs":"DO-141","name":"Tamayo","district":"","country":"DO","canton":"Baoruco Province","population":26772,"has_mx":false,"reason":"No MX records found"},{"provider":"unknown","domain":"","bfs":"DO-142","name":"Tamboríl","district":"","country":"DO","canton":"Santiago Province","osm_relation_id":7380703,"population":51695,"has_mx":false,"reason":"No MX records found"},{"provider":"unknown","domain":"","bfs":"DO-143","name":"Tenares","district":"","country":"DO","canton":"Hermanas Mirabal Province","osm_relation_id":7386647,"population":27765,"has_mx":false,"reason":"No MX records found"},{"provider":"unknown","domain":"","bfs":"DO-144","name":"Vallejuelo","district":"","country":"DO","canton":"San Juan Province","osm_relation_id":7155992,"population":12403,"has_mx":false,"reason":"No MX records found"},{"provider":"unknown","domain":"","bfs":"DO-145","name":"Vicente Noble","district":"","country":"DO","canton":"Barahona Province","osm_relation_id":7151616,"population":21605,"has_mx":false,"reason":"No MX records found"},{"provider":"unknown","domain":"","bfs":"DO-146","name":"Villa Altagracia","district":"","country":"DO","canton":"San Cristóbal Province","osm_relation_id":7159844,"population":84312,"has_mx":false,"reason":"No MX records found"},{"provider":"unknown","domain":"","bfs":"DO-147","name":"Villa González","district":"","country":"DO","canton":"Santiago Province","osm_relation_id":7373398,"population":37349,"has_mx":false,"reason":"No MX records found"},{"provider":"unknown","domain":"","bfs":"DO-148","name":"Villa Hermosa","district":"","country":"DO","canton":"La Romana","osm_relation_id":7405581,"population":89204,"has_mx":false,"reason":"No MX records found"},{"provider":"unknown","domain":"","bfs":"DO-149","name":"Villa Isabela","district":"","country":"DO","canton":"Puerto Plata Province","population":17169,"has_mx":false,"reason":"No MX records found"},{"provider":"unknown","domain":"","bfs":"DO-150","name":"Villa Los Almácigos","district":"","country":"DO","canton":"Santiago Rodríguez Province","osm_relation_id":7390993,"population":11183,"has_mx":false,"reason":"No MX records found"},{"provider":"unknown","domain":"","bfs":"DO-151","name":"Villa Montellano","district":"","country":"DO","canton":"Puerto Plata Province","osm_relation_id":7373133,"population":19717,"has_mx":false,"reason":"No MX records found"},{"provider":"unknown","domain":"","bfs":"DO-152","name":"Villa Riva","district":"","country":"DO","canton":"Duarte Province","osm_relation_id":7386377,"population":33663,"has_mx":false,"reason":"No MX records found"},{"provider":"unknown","domain":"","bfs":"DO-153","name":"Villa Tapia","district":"","country":"DO","canton":"Hermanas Mirabal Province","osm_relation_id":7386660,"population":26159,"has_mx":false,"reason":"No MX records found"},{"provider":"unknown","domain":"","bfs":"DO-154","name":"Villa Vásquez","district":"","country":"DO","canton":"Monte Cristi Province","osm_relation_id":7167186,"population":14424,"has_mx":false,"reason":"No MX records found"},{"provider":"unknown","domain":"","bfs":"DO-155","name":"Yaguate","district":"","country":"DO","canton":"San Cristóbal Province","osm_relation_id":7159850,"population":51489,"has_mx":false,"reason":"No MX records found"},{"provider":"unknown","domain":"","bfs":"DO-156","name":"Yamasá","district":"","country":"DO","canton":"Monte Plata Province","osm_relation_id":7405676,"population":55348,"has_mx":false,"reason":"No MX records found"}]