[{"bfs":"SB-001","country":"SB","osm_relation_id":2536258,"provider":"unknown","domain":"","name":"Central Province","district":"","canton":"Solomon Islands","has_mx":false,"reason":"No MX records found"},{"bfs":"SB-002","country":"SB","osm_relation_id":2536259,"provider":"unknown","domain":"","name":"Choiseul Province","district":"","canton":"Solomon Islands","has_mx":false,"reason":"No MX records found"},{"bfs":"SB-003","population":93613,"country":"SB","osm_relation_id":11916914,"provider":"unknown","domain":"","name":"Guadalcanal Province","district":"","canton":"Solomon Islands","has_mx":false,"reason":"No MX records found"},{"bfs":"SB-004","country":"SB","osm_relation_id":2536261,"provider":"unknown","domain":"","name":"Isabel Province","district":"","canton":"Solomon Islands","has_mx":false,"reason":"No MX records found"},{"bfs":"SB-005","country":"SB","osm_relation_id":2536262,"provider":"unknown","domain":"","name":"Makira-Ulawa Province","district":"","canton":"Solomon Islands","has_mx":false,"reason":"No MX records found"},{"bfs":"SB-006","country":"SB","osm_relation_id":2536263,"provider":"unknown","domain":"","name":"Malaita Province","district":"","canton":"Solomon Islands","has_mx":false,"reason":"No MX records found"},{"bfs":"SB-007","country":"SB","osm_relation_id":2536264,"provider":"unknown","domain":"","name":"Rennell and Bellona Province","district":"","canton":"Solomon Islands","has_mx":false,"reason":"No MX records found"},{"bfs":"SB-008","population":21362,"country":"SB","osm_relation_id":2536265,"provider":"unknown","domain":"","name":"Temotu Province","district":"","canton":"Solomon Islands","has_mx":false,"reason":"No MX records found"},{"bfs":"SB-009","country":"SB","osm_relation_id":11916824,"provider":"unknown","domain":"","name":"Western Province","district":"","canton":"Solomon Islands","has_mx":false,"reason":"No MX records found"}]