[{"bfs":"SV-001","canton":"Western Sonsonate","name":"Acajutla","provider":"microsoft","osm_relation_id":5977122,"population":55307,"district":"","country":"SV","mx_countries":["US"],"domain":"acajutla.gob.sv","has_mx":true,"mx":["acajutla-gob-sv.mail.protection.outlook.com"],"reason":"MX record (acajutla-gob-sv.mail.protection.outlook.com) matches Microsoft","spf":"v=spf1 include:spf.protection.outlook.com -all","autodiscover":{"autodiscover_cname":"autodiscover.outlook.com"},"dkim":{"selector1":"selector1-acajutla-gob-sv._domainkey.alcaldiaacajutlagob.p-v1.dkim.mail.microsoft","selector2":"selector2-acajutla-gob-sv._domainkey.alcaldiaacajutlagob.p-v1.dkim.mail.microsoft"}},{"bfs":"SV-002","canton":"Central Chalatenango","name":"Agua Caliente","provider":"unknown","osm_relation_id":19564030,"population":7341,"district":"","country":"SV","domain":"","has_mx":false,"reason":"No MX records found"},{"bfs":"SV-003","canton":"Northern San Salvador","name":"Aguilares","provider":"unknown","osm_relation_id":9229624,"population":21051,"district":"","country":"SV","domain":"","has_mx":false,"reason":"No MX records found"},{"bfs":"SV-004","canton":"Central Ahuachapán","name":"Ahuachapán","provider":"unknown","osm_relation_id":6744515,"population":127301,"district":"","country":"SV","domain":"","has_mx":false,"reason":"No MX records found"},{"bfs":"SV-005","canton":"Northern Usulután","name":"Alegría","provider":"unknown","osm_relation_id":19560744,"population":12294,"district":"","country":"SV","domain":"","has_mx":false,"reason":"No MX records found"},{"bfs":"SV-006","canton":"Northern La Unión","name":"Anamorós","provider":"unknown","osm_relation_id":19563640,"population":14210,"district":"","country":"SV","domain":"","has_mx":false,"reason":"No MX records found"},{"bfs":"SV-007","canton":"Eastern La Libertad","name":"Antiguo Cuscatlán","provider":"independent","osm_relation_id":6805100,"population":37451,"district":"","country":"SV","mx_countries":["US"],"domain":"lalibertadeste.gob.sv","has_mx":true,"mx":["lalibertadeste.gob.sv"],"reason":"MX (lalibertadeste.gob.sv) is self-hosted","spf":"v=spf1 ip4:209.188.21.92 +a +mx include:spf.antispamcloud.com ~all","autodiscover":{"autodiscover_srv":"cpanelemaildiscovery.cpanel.net"}},{"bfs":"SV-008","canton":"Central Ahuachapán","name":"Apaneca","provider":"unknown","osm_relation_id":6626641,"population":9436,"district":"","country":"SV","domain":"","has_mx":false,"reason":"No MX records found"},{"bfs":"SV-009","canton":"Northern San Vicente","name":"Apastepeque","provider":"unknown","osm_relation_id":19560284,"population":19646,"district":"","country":"SV","domain":"","has_mx":false,"reason":"No MX records found"},{"bfs":"SV-010","canton":"Western San Salvador","name":"Apopa","provider":"independent","gateway":"mailspamprotection","osm_relation_id":9229558,"population":129083,"district":"","country":"SV","mx_countries":["US"],"domain":"alcaldiasansalvadoroeste.com","has_mx":true,"mx":["mx10.antispam.mailspamprotection.com","mx20.antispam.mailspamprotection.com","mx30.antispam.mailspamprotection.com"],"reason":"MX is mailspamprotection gateway; backend provider unknown","spf":"v=spf1 +a +mx include:_spf.mail.siteground.net include:alcaldiasansalvadoroeste.com.spf.auto.dnssmarthost.net ~all"},{"bfs":"SV-011","canton":"Northern Morazán","name":"Arambala","provider":"unknown","osm_relation_id":19560554,"population":3861,"district":"","country":"SV","domain":"","has_mx":false,"reason":"No MX records found"},{"bfs":"SV-012","canton":"Southern Chalatenango","name":"Arcatao","provider":"unknown","osm_relation_id":19564017,"population":2252,"district":"","country":"SV","domain":"","has_mx":false,"reason":"No MX records found"},{"bfs":"SV-013","canton":"Eastern Sonsonate","name":"Armenia","provider":"unknown","osm_relation_id":6651387,"population":35926,"district":"","country":"SV","domain":"","has_mx":false,"reason":"No MX records found"},{"bfs":"SV-014","canton":"Northern Ahuachapán","name":"Atiquizaya","provider":"unknown","osm_relation_id":9620563,"population":34209,"district":"","country":"SV","domain":"","has_mx":false,"reason":"No MX records found"},{"bfs":"SV-015","canton":"Central San Salvador","name":"Ayutuxtepeque","provider":"unknown","osm_relation_id":6873233,"population":31631,"district":"","country":"SV","domain":"","has_mx":false,"reason":"No MX records found"},{"bfs":"SV-016","canton":"Southern Chalatenango","name":"Azacualpa","provider":"unknown","osm_relation_id":19563801,"population":1053,"district":"","country":"SV","domain":"","has_mx":false,"reason":"No MX records found"},{"bfs":"SV-017","canton":"Northern Usulután","name":"Berlín","provider":"unknown","osm_relation_id":19560755,"population":20683,"district":"","country":"SV","domain":"","has_mx":false,"reason":"No MX records found"},{"bfs":"SV-018","canton":"Northern La Unión","name":"Bolívar","provider":"unknown","osm_relation_id":19563648,"population":3482,"district":"","country":"SV","domain":"","has_mx":false,"reason":"No MX records found"},{"bfs":"SV-019","canton":"Northern Morazán","name":"Cacaopera","provider":"unknown","osm_relation_id":19560578,"population":10488,"district":"","country":"SV","domain":"","has_mx":false,"reason":"No MX records found"},{"bfs":"SV-020","canton":"Eastern Usulután","name":"California","provider":"unknown","osm_relation_id":19560761,"population":2619,"district":"","country":"SV","domain":"","has_mx":false,"reason":"No MX records found"},{"bfs":"SV-021","canton":"Eastern Sonsonate","name":"Caluco","provider":"unknown","osm_relation_id":13128742,"population":10330,"district":"","country":"SV","domain":"","has_mx":false,"reason":"No MX records found"},{"bfs":"SV-022","canton":"Southern Cuscatlán","name":"Candelaria","provider":"unknown","osm_relation_id":8022709,"population":11307,"district":"","country":"SV","domain":"","has_mx":false,"reason":"No MX records found"},{"bfs":"SV-023","canton":"Western Santa Ana","name":"Candelaria de la Frontera","provider":"unknown","osm_relation_id":8527341,"population":23229,"district":"","country":"SV","domain":"","has_mx":false,"reason":"No MX records found"},{"bfs":"SV-024","canton":"Northern San Miguel","name":"Carolina","provider":"unknown","osm_relation_id":19560347,"population":6419,"district":"","country":"SV","domain":"","has_mx":false,"reason":"No MX records found"},{"bfs":"SV-025","canton":"Southern Chalatenango","name":"Chalatenango","provider":"microsoft","osm_relation_id":19563800,"population":30679,"district":"","country":"SV","mx_countries":["US"],"domain":"chalatenango.gob.sv","has_mx":true,"mx":["chalatenango-gob-sv.mail.protection.outlook.com"],"reason":"MX record (chalatenango-gob-sv.mail.protection.outlook.com) matches Microsoft","spf":"v=spf1 include:spf.protection.outlook.com -all","autodiscover":{"autodiscover_cname":"autodiscover.outlook.com"}},{"bfs":"SV-026","canton":"Western Santa Ana","name":"Chalchuapa","provider":"unknown","osm_relation_id":8527345,"population":74025,"district":"","country":"SV","domain":"","has_mx":false,"reason":"No MX records found"},{"bfs":"SV-027","canton":"Northern San Miguel","name":"Chapeltique","provider":"unknown","osm_relation_id":19560370,"population":11295,"district":"","country":"SV","domain":"","has_mx":false,"reason":"No MX records found"},{"bfs":"SV-028","canton":"Southern Morazán","name":"Chilanga","provider":"unknown","osm_relation_id":19560767,"population":9610,"district":"","country":"SV","domain":"","has_mx":false,"reason":"No MX records found"},{"bfs":"SV-029","canton":"Coastal La Libertad","name":"Chiltiupán","provider":"unknown","osm_relation_id":7369381,"population":10914,"district":"","country":"SV","domain":"","has_mx":false,"reason":"No MX records found"},{"bfs":"SV-030","canton":"Western San Miguel","name":"Chinameca","provider":"unknown","osm_relation_id":19560408,"population":24142,"district":"","country":"SV","domain":"","has_mx":false,"reason":"No MX records found"},{"bfs":"SV-031","canton":"Central San Miguel","name":"Chirilagua","provider":"unknown","osm_relation_id":19560506,"population":19368,"district":"","country":"SV","domain":"","has_mx":false,"reason":"No MX records found"},{"bfs":"SV-032","canton":"Western Cabañas","name":"Cinquera","provider":"unknown","osm_relation_id":19560306,"population":2096,"district":"","country":"SV","domain":"","has_mx":false,"reason":"No MX records found"},{"bfs":"SV-033","canton":"Northern Chalatenango","name":"Citalá","provider":"unknown","osm_relation_id":13284888,"population":4581,"district":"","country":"SV","domain":"","has_mx":false,"reason":"No MX records found"},{"bfs":"SV-034","canton":"Central La Libertad","name":"Ciudad Arce","provider":"unknown","osm_relation_id":6678084,"population":65550,"district":"","country":"SV","domain":"","has_mx":false,"reason":"No MX records found"},{"bfs":"SV-035","canton":"Northern San Miguel","name":"Ciudad Barrios","provider":"unknown","osm_relation_id":19560519,"population":23256,"district":"","country":"SV","domain":"","has_mx":false,"reason":"No MX records found"},{"bfs":"SV-036","canton":"Central San Salvador","name":"Ciudad Delgado","provider":"unknown","osm_relation_id":9229415,"population":106367,"district":"","country":"SV","domain":"","has_mx":false,"reason":"No MX records found"},{"bfs":"SV-037","canton":"Eastern Santa Ana","name":"Coatepeque","provider":"unknown","osm_relation_id":13128867,"population":36371,"district":"","country":"SV","domain":"","has_mx":false,"reason":"No MX records found"},{"bfs":"SV-038","canton":"Southern Cuscatlán","name":"Cojutepeque","provider":"independent","osm_relation_id":9222747,"population":46839,"district":"","country":"SV","mx_countries":["US"],"domain":"cuscatlansur.gob.sv","has_mx":true,"mx":["mx1.hostinger.com","mx2.hostinger.com"],"reason":"MX (mx1.hostinger.com, mx2.hostinger.com) is self-hosted","spf":"v=spf1 include:_spf.mail.hostinger.com ~all","autodiscover":{"autodiscover_cname":"autodiscover.mail.hostinger.com"}},{"bfs":"SV-039","canton":"Western La Libertad","name":"Colón","provider":"local-isp","osm_relation_id":19563383,"population":130513,"district":"","country":"SV","isp_name":"OVH (FR)","mx_countries":["CA"],"domain":"colon.gob.sv","has_mx":true,"mx":["colon.gob.sv"],"reason":"MX (colon.gob.sv) hosted on Local ISP (OVH (FR))","spf":"v=spf1 +a +mx +ip4:51.79.72.49 ~all","autodiscover":{"autodiscover_srv":"cpanelemaildiscovery.cpanel.net"}},{"bfs":"SV-040","canton":"Central San Miguel","name":"Comacarán","provider":"unknown","osm_relation_id":19560533,"population":3451,"district":"","country":"SV","domain":"","has_mx":false,"reason":"No MX records found"},{"bfs":"SV-041","canton":"Southern Chalatenango","name":"Comalapa","provider":"unknown","osm_relation_id":19564035,"population":4136,"district":"","country":"SV","domain":"","has_mx":false,"reason":"No MX records found"},{"bfs":"SV-042","canton":"Southern La Libertad","name":"Comasagua","provider":"unknown","osm_relation_id":19563423,"population":12705,"district":"","country":"SV","domain":"","has_mx":false,"reason":"No MX records found"},{"bfs":"SV-043","canton":"Eastern Usulután","name":"Concepción Batres","provider":"unknown","osm_relation_id":19560879,"population":10840,"district":"","country":"SV","domain":"","has_mx":false,"reason":"No MX records found"},{"bfs":"SV-044","canton":"Southern Chalatenango","name":"Concepción Quezaltepeque","provider":"unknown","osm_relation_id":19563650,"population":6011,"district":"","country":"SV","domain":"","has_mx":false,"reason":"No MX records found"},{"bfs":"SV-045","canton":"Central Ahuachapán","name":"Concepción de Ataco","provider":"unknown","osm_relation_id":6173339,"population":12968,"district":"","country":"SV","domain":"","has_mx":false,"reason":"No MX records found"},{"bfs":"SV-046","canton":"Northern La Unión","name":"Concepción de Oriente","provider":"unknown","osm_relation_id":19563653,"population":7042,"district":"","country":"SV","domain":"","has_mx":false,"reason":"No MX records found"},{"bfs":"SV-047","canton":"Southern La Unión","name":"Conchagua","provider":"unknown","osm_relation_id":6560289,"population":24919,"district":"","country":"SV","domain":"","has_mx":false,"reason":"No MX records found"},{"bfs":"SV-048","canton":"Northern Morazán","name":"Corinto","provider":"unknown","osm_relation_id":8811961,"population":14847,"district":"","country":"SV","domain":"","has_mx":false,"reason":"No MX records found"},{"bfs":"SV-049","canton":"Eastern Sonsonate","name":"Cuisnahuat","provider":"unknown","osm_relation_id":13128748,"population":12421,"district":"","country":"SV","domain":"","has_mx":false,"reason":"No MX records found"},{"bfs":"SV-050","canton":"Central San Salvador","name":"Cuscatancingo","provider":"unknown","osm_relation_id":6867826,"population":68137,"district":"","country":"SV","domain":"","has_mx":false,"reason":"No MX records found"},{"bfs":"SV-051","canton":"Western La Paz","name":"Cuyultitán","provider":"unknown","osm_relation_id":19563473,"population":6313,"district":"","country":"SV","domain":"","has_mx":false,"reason":"No MX records found"},{"bfs":"SV-052","canton":"Southern Morazán","name":"Delicias de Concepción","provider":"unknown","osm_relation_id":19560779,"population":4621,"district":"","country":"SV","domain":"","has_mx":false,"reason":"No MX records found"},{"bfs":"SV-053","canton":"Eastern Cabañas","name":"Dolores","provider":"unknown","osm_relation_id":12653303,"population":6267,"district":"","country":"SV","domain":"","has_mx":false,"reason":"No MX records found"},{"bfs":"SV-054","canton":"Central Chalatenango","name":"Dulce Nombre de María","provider":"unknown","osm_relation_id":19563639,"population":4708,"district":"","country":"SV","domain":"","has_mx":false,"reason":"No MX records found"},{"bfs":"SV-055","canton":"Southern Cuscatlán","name":"El Carmen","provider":"unknown","osm_relation_id":19563312,"population":15961,"district":"","country":"SV","domain":"","has_mx":false,"reason":"No MX records found"},{"bfs":"SV-056","canton":"Southern La Unión","name":"El Carmen","provider":"unknown","osm_relation_id":8283252,"population":13611,"district":"","country":"SV","domain":"","has_mx":false,"reason":"No MX records found"},{"bfs":"SV-057","canton":"Southern Chalatenango","name":"El Carrizal","provider":"unknown","osm_relation_id":19563615,"population":2235,"district":"","country":"SV","domain":"","has_mx":false,"reason":"No MX records found"},{"bfs":"SV-058","canton":"Eastern Santa Ana","name":"El Congo","provider":"unknown","osm_relation_id":13128868,"population":27587,"district":"","country":"SV","domain":"","has_mx":false,"reason":"No MX records found"},{"bfs":"SV-059","canton":"Southern Morazán","name":"El Divisadero","provider":"unknown","osm_relation_id":19560840,"population":7177,"district":"","country":"SV","domain":"","has_mx":false,"reason":"No MX records found"},{"bfs":"SV-060","canton":"Northern San Salvador","name":"El Paisnal","provider":"unknown","osm_relation_id":6433677,"population":15469,"district":"","country":"SV","domain":"","has_mx":false,"reason":"No MX records found"},{"bfs":"SV-061","canton":"Central Chalatenango","name":"El Paraíso","provider":"unknown","osm_relation_id":19563609,"population":11622,"district":"","country":"SV","domain":"","has_mx":false,"reason":"No MX records found"},{"bfs":"SV-062","canton":"Western Santa Ana","name":"El Porvenir","provider":"unknown","osm_relation_id":8196206,"population":12721,"district":"","country":"SV","domain":"","has_mx":false,"reason":"No MX records found"},{"bfs":"SV-063","canton":"Northern Ahuachapán","name":"El Refugio","provider":"unknown","osm_relation_id":9620562,"population":9827,"district":"","country":"SV","domain":"","has_mx":false,"reason":"No MX records found"},{"bfs":"SV-064","canton":"Northern Morazán","name":"El Rosario","provider":"unknown","osm_relation_id":19512041,"population":1310,"district":"","country":"SV","domain":"","has_mx":false,"reason":"No MX records found"},{"bfs":"SV-065","canton":"Central La Paz","name":"El Rosario","provider":"unknown","osm_relation_id":8418085,"population":17551,"district":"","country":"SV","domain":"","has_mx":false,"reason":"No MX records found"},{"bfs":"SV-066","canton":"Southern Cuscatlán","name":"El Rosario","provider":"unknown","osm_relation_id":19563313,"population":3639,"district":"","country":"SV","domain":"","has_mx":false,"reason":"No MX records found"},{"bfs":"SV-067","canton":"Northern La Unión","name":"El Sauce","provider":"unknown","osm_relation_id":19563776,"population":6506,"district":"","country":"SV","domain":"","has_mx":false,"reason":"No MX records found"},{"bfs":"SV-068","canton":"Northern Usulután","name":"El Triunfo","provider":"unknown","osm_relation_id":19560962,"population":7099,"district":"","country":"SV","domain":"","has_mx":false,"reason":"No MX records found"},{"bfs":"SV-069","canton":"Western San Miguel","name":"El Tránsito","provider":"unknown","osm_relation_id":19560547,"population":17057,"district":"","country":"SV","domain":"","has_mx":false,"reason":"No MX records found"},{"bfs":"SV-070","canton":"Eastern Usulután","name":"Ereguayquín","provider":"unknown","osm_relation_id":19560979,"population":6618,"district":"","country":"SV","domain":"","has_mx":false,"reason":"No MX records found"},{"bfs":"SV-071","canton":"Northern Usulután","name":"Estanzuelas","provider":"unknown","osm_relation_id":19560993,"population":7761,"district":"","country":"SV","domain":"","has_mx":false,"reason":"No MX records found"},{"bfs":"SV-072","canton":"Eastern Cabañas","name":"Guacotecti","provider":"unknown","osm_relation_id":10303109,"population":7585,"district":"","country":"SV","domain":"","has_mx":false,"reason":"No MX records found"},{"bfs":"SV-073","canton":"Southern San Vicente","name":"Guadalupe","provider":"unknown","osm_relation_id":19560304,"population":5851,"district":"","country":"SV","domain":"","has_mx":false,"reason":"No MX records found"},{"bfs":"SV-074","canton":"Southern Morazán","name":"Gualococti","provider":"unknown","osm_relation_id":19560882,"population":4263,"district":"","country":"SV","domain":"","has_mx":false,"reason":"No MX records found"},{"bfs":"SV-075","canton":"Southern Morazán","name":"Guatajiagua","provider":"unknown","osm_relation_id":19560948,"population":10237,"district":"","country":"SV","domain":"","has_mx":false,"reason":"No MX records found"},{"bfs":"SV-076","canton":"Southern Ahuachapán","name":"Guaymango","provider":"unknown","osm_relation_id":6626607,"population":21607,"district":"","country":"SV","domain":"","has_mx":false,"reason":"No MX records found"},{"bfs":"SV-077","canton":"Northern San Salvador","name":"Guazapa","provider":"unknown","osm_relation_id":9229449,"population":25344,"district":"","country":"SV","domain":"","has_mx":false,"reason":"No MX records found"},{"bfs":"SV-078","canton":"Eastern La Libertad","name":"Huizúcar","provider":"unknown","osm_relation_id":19563428,"population":12287,"district":"","country":"SV","domain":"","has_mx":false,"reason":"No MX records found"},{"bfs":"SV-079","canton":"Western Cabañas","name":"Ilobasco","provider":"google","osm_relation_id":19560333,"population":58581,"district":"","country":"SV","mx_countries":["US"],"domain":"alcaldiailobasco.gob.sv","has_mx":true,"mx":["alt1.aspmx.l.google.com","alt2.aspmx.l.google.com","alt3.aspmx.l.google.com","alt4.aspmx.l.google.com","aspmx.l.google.com"],"reason":"MX record (alt1.aspmx.l.google.com, alt2.aspmx.l.google.com) matches Google","spf":"v=spf1 +a +mx +ip4:152.53.39.110 include:_spf.google.com ~all"},{"bfs":"SV-080","canton":"Eastern San Salvador","name":"Ilopango","provider":"unknown","osm_relation_id":8147955,"population":88824,"district":"","country":"SV","domain":"","has_mx":false,"reason":"No MX records found"},{"bfs":"SV-081","canton":"Southern La Unión","name":"Intipucá","provider":"unknown","osm_relation_id":8283242,"population":6785,"district":"","country":"SV","domain":"","has_mx":false,"reason":"No MX records found"},{"bfs":"SV-082","canton":"Eastern Sonsonate","name":"Izalco","provider":"independent","osm_relation_id":6946258,"population":77529,"district":"","country":"SV","domain":"sonsonateeste.gob.sv","has_mx":true,"mx":["_dc-mx.392d2ecccbb6.sonsonateeste.gob.sv"],"reason":"MX (_dc-mx.392d2ecccbb6.sonsonateeste.gob.sv) is self-hosted","spf":"v=spf1 +a +mx +ip4:51.79.72.49 ~all","txt_verifications":{"google":"9KBWfk2zDfT04Kh0IwBYoot8GCyjJYJLZ0LDCN_zDEw"}},{"bfs":"SV-083","canton":"Western La Libertad","name":"Jayaque","provider":"unknown","osm_relation_id":7369614,"population":16391,"district":"","country":"SV","domain":"","has_mx":false,"reason":"No MX records found"},{"bfs":"SV-084","canton":"Central La Paz","name":"Jerusalén","provider":"unknown","osm_relation_id":6594206,"population":2586,"district":"","country":"SV","domain":"","has_mx":false,"reason":"No MX records found"},{"bfs":"SV-085","canton":"Coastal La Libertad","name":"Jicalapa","provider":"unknown","osm_relation_id":7369369,"population":6132,"district":"","country":"SV","domain":"","has_mx":false,"reason":"No MX records found"},{"bfs":"SV-086","canton":"Western Usulután","name":"Jiquilisco","provider":"unknown","osm_relation_id":19563792,"population":44271,"district":"","country":"SV","domain":"","has_mx":false,"reason":"No MX records found"},{"bfs":"SV-087","canton":"Northern Morazán","name":"Joateca","provider":"unknown","osm_relation_id":19560978,"population":3831,"district":"","country":"SV","domain":"","has_mx":false,"reason":"No MX records found"},{"bfs":"SV-088","canton":"Northern Morazán","name":"Jocoaitique","provider":"unknown","osm_relation_id":19512042,"population":4253,"district":"","country":"SV","domain":"","has_mx":false,"reason":"No MX records found"},{"bfs":"SV-089","canton":"Southern Morazán","name":"Jocoro","provider":"unknown","osm_relation_id":19560992,"population":9658,"district":"","country":"SV","domain":"","has_mx":false,"reason":"No MX records found"},{"bfs":"SV-090","canton":"Northern Sonsonate","name":"Juayúa","provider":"unknown","osm_relation_id":6955011,"population":24344,"district":"","country":"SV","domain":"","has_mx":false,"reason":"No MX records found"},{"bfs":"SV-091","canton":"Northern Usulután","name":"Jucuapa","provider":"unknown","osm_relation_id":19561034,"population":17696,"district":"","country":"SV","domain":"","has_mx":false,"reason":"No MX records found"},{"bfs":"SV-092","canton":"Eastern Usulután","name":"Jucuarán","provider":"unknown","osm_relation_id":10298565,"population":12722,"district":"","country":"SV","domain":"","has_mx":false,"reason":"No MX records found"},{"bfs":"SV-093","canton":"Southern Ahuachapán","name":"Jujutla","provider":"unknown","osm_relation_id":6172140,"population":27415,"district":"","country":"SV","domain":"","has_mx":false,"reason":"No MX records found"},{"bfs":"SV-094","canton":"Western Cabañas","name":"Jutiapa","provider":"unknown","osm_relation_id":19560440,"population":7129,"district":"","country":"SV","domain":"","has_mx":false,"reason":"No MX records found"},{"bfs":"SV-095","canton":"Southern Chalatenango","name":"La Laguna","provider":"unknown","osm_relation_id":19563606,"population":3988,"district":"","country":"SV","domain":"","has_mx":false,"reason":"No MX records found"},{"bfs":"SV-096","canton":"Coastal La Libertad","name":"La Libertad","provider":"unknown","osm_relation_id":7369049,"population":44761,"district":"","country":"SV","domain":"","has_mx":false,"reason":"No MX records found"},{"bfs":"SV-097","canton":"Northern Chalatenango","name":"La Palma","provider":"unknown","osm_relation_id":19563595,"population":13066,"district":"","country":"SV","domain":"","has_mx":false,"reason":"No MX records found"},{"bfs":"SV-098","canton":"Central Chalatenango","name":"La Reina","provider":"unknown","osm_relation_id":19563578,"population":7583,"district":"","country":"SV","domain":"","has_mx":false,"reason":"No MX records found"},{"bfs":"SV-099","canton":"Southern La Unión","name":"La Unión","provider":"unknown","osm_relation_id":6553305,"population":40129,"district":"","country":"SV","domain":"","has_mx":false,"reason":"No MX records found"},{"bfs":"SV-100","canton":"Southern Chalatenango","name":"Las Flores","provider":"unknown","osm_relation_id":19563544,"population":1301,"district":"","country":"SV","domain":"","has_mx":false,"reason":"No MX records found"},{"bfs":"SV-101","canton":"Southern Chalatenango","name":"Las Vueltas","provider":"unknown","osm_relation_id":19563526,"population":1609,"district":"","country":"SV","domain":"","has_mx":false,"reason":"No MX records found"},{"bfs":"SV-102","canton":"Northern La Unión","name":"Lislique","provider":"unknown","osm_relation_id":19563797,"population":12732,"district":"","country":"SV","domain":"","has_mx":false,"reason":"No MX records found"},{"bfs":"SV-103","canton":"Western San Miguel","name":"Lolotique","provider":"unknown","osm_relation_id":19560555,"population":15007,"district":"","country":"SV","domain":"","has_mx":false,"reason":"No MX records found"},{"bfs":"SV-104","canton":"Southern Morazán","name":"Lolotiquillo","provider":"unknown","osm_relation_id":19561007,"population":4592,"district":"","country":"SV","domain":"","has_mx":false,"reason":"No MX records found"},{"bfs":"SV-105","canton":"Northern Santa Ana","name":"Masahuat","provider":"unknown","osm_relation_id":6525328,"population":2762,"district":"","country":"SV","domain":"","has_mx":false,"reason":"No MX records found"},{"bfs":"SV-106","canton":"Northern Morazán","name":"Meanguera","provider":"unknown","osm_relation_id":12017123,"population":6720,"district":"","country":"SV","domain":"","has_mx":false,"reason":"No MX records found"},{"bfs":"SV-107","canton":"Southern La Unión","name":"Meanguera del Golfo","provider":"unknown","osm_relation_id":19563814,"population":2134,"district":"","country":"SV","domain":"","has_mx":false,"reason":"No MX records found"},{"bfs":"SV-108","canton":"Central San Salvador","name":"Mejicanos","provider":"unknown","osm_relation_id":6846481,"population":136641,"district":"","country":"SV","domain":"","has_mx":false,"reason":"No MX records found"},{"bfs":"SV-109","canton":"Central La Paz","name":"Mercedes La Ceiba","provider":"unknown","osm_relation_id":6594216,"population":632,"district":"","country":"SV","domain":"","has_mx":false,"reason":"No MX records found"},{"bfs":"SV-110","canton":"Northern Usulután","name":"Mercedes Umaña","provider":"unknown","osm_relation_id":19561039,"population":12547,"district":"","country":"SV","domain":"","has_mx":false,"reason":"No MX records found"},{"bfs":"SV-111","canton":"Northern Santa Ana","name":"Metapán","provider":"microsoft","osm_relation_id":6525275,"population":63763,"district":"","country":"SV","mx_countries":["US"],"domain":"santaananorte.gob.sv","has_mx":true,"mx":["santaananorte-gob-sv.mail.protection.outlook.com"],"reason":"MX record (santaananorte-gob-sv.mail.protection.outlook.com) matches Microsoft","spf":"v=spf1 include:spf.protection.outlook.com ~all","autodiscover":{"autodiscover_cname":"autodiscover.outlook.com"}},{"bfs":"SV-112","canton":"Central San Miguel","name":"Moncagua","provider":"unknown","osm_relation_id":19560557,"population":24167,"district":"","country":"SV","domain":"","has_mx":false,"reason":"No MX records found"},{"bfs":"SV-113","canton":"Southern Cuscatlán","name":"Monte San Juan","provider":"unknown","osm_relation_id":19563315,"population":12239,"district":"","country":"SV","domain":"","has_mx":false,"reason":"No MX records found"},{"bfs":"SV-114","canton":"Northern Sonsonate","name":"Nahuizalco","provider":"unknown","osm_relation_id":13128806,"population":55641,"district":"","country":"SV","domain":"","has_mx":false,"reason":"No MX records found"},{"bfs":"SV-115","canton":"Central Sonsonate","name":"Nahulingo","provider":"unknown","osm_relation_id":13128761,"population":10199,"district":"","country":"SV","domain":"","has_mx":false,"reason":"No MX records found"},{"bfs":"SV-116","canton":"Western San Salvador","name":"Nejapa","provider":"unknown","osm_relation_id":9229622,"population":35673,"district":"","country":"SV","domain":"","has_mx":false,"reason":"No MX records found"},{"bfs":"SV-117","canton":"Southern Chalatenango","name":"Nombre de Jesús","provider":"unknown","osm_relation_id":19563516,"population":4017,"district":"","country":"SV","domain":"","has_mx":false,"reason":"No MX records found"},{"bfs":"SV-118","canton":"Central Chalatenango","name":"Nueva Concepción","provider":"unknown","osm_relation_id":13287651,"population":27209,"district":"","country":"SV","domain":"","has_mx":false,"reason":"No MX records found"},{"bfs":"SV-119","canton":"Northern La Unión","name":"Nueva Esparta","provider":"unknown","osm_relation_id":19563910,"population":8638,"district":"","country":"SV","domain":"","has_mx":false,"reason":"No MX records found"},{"bfs":"SV-120","canton":"Northern Usulután","name":"Nueva Granada","provider":"unknown","osm_relation_id":19561046,"population":7278,"district":"","country":"SV","domain":"","has_mx":false,"reason":"No MX records found"},{"bfs":"SV-121","canton":"Western San Miguel","name":"Nueva Guadalupe","provider":"unknown","osm_relation_id":19560560,"population":7747,"district":"","country":"SV","domain":"","has_mx":false,"reason":"No MX records found"},{"bfs":"SV-122","canton":"Southern Chalatenango","name":"Nueva Trinidad","provider":"unknown","osm_relation_id":19563499,"population":1672,"district":"","country":"SV","domain":"","has_mx":false,"reason":"No MX records found"},{"bfs":"SV-123","canton":"Eastern La Libertad","name":"Nuevo Cuscatlán","provider":"unknown","osm_relation_id":19563431,"population":12699,"district":"","country":"SV","domain":"","has_mx":false,"reason":"No MX records found"},{"bfs":"SV-124","canton":"Northern San Miguel","name":"Nuevo Edén de San Juan","provider":"unknown","osm_relation_id":19560593,"population":3791,"district":"","country":"SV","domain":"","has_mx":false,"reason":"No MX records found"},{"bfs":"SV-125","canton":"Southern Chalatenango","name":"Ojos de Agua","provider":"unknown","osm_relation_id":19563450,"population":3023,"district":"","country":"SV","domain":"","has_mx":false,"reason":"No MX records found"},{"bfs":"SV-126","canton":"Western La Paz","name":"Olocuilta","provider":"independent","osm_relation_id":19563511,"population":30989,"district":"","country":"SV","mx_countries":["GB"],"domain":"olocuilta.gob.sv","has_mx":true,"mx":["mx.stackmail.com"],"reason":"MX (mx.stackmail.com) is self-hosted","autodiscover":{"autodiscover_cname":"autodiscover.stackmail.com"}},{"bfs":"SV-127","canton":"Northern Cuscatlán","name":"Oratorio de Concepción","provider":"unknown","osm_relation_id":9222624,"population":3748,"district":"","country":"SV","domain":"","has_mx":false,"reason":"No MX records found"},{"bfs":"SV-128","canton":"Southern Morazán","name":"Osicala","provider":"unknown","osm_relation_id":19561035,"population":9177,"district":"","country":"SV","domain":"","has_mx":false,"reason":"No MX records found"},{"bfs":"SV-129","canton":"Eastern Usulután","name":"Ozatlán","provider":"unknown","osm_relation_id":19563816,"population":10497,"district":"","country":"SV","domain":"","has_mx":false,"reason":"No MX records found"},{"bfs":"SV-130","canton":"Southern San Salvador","name":"Panchimalco","provider":"unknown","osm_relation_id":13298479,"population":44404,"district":"","country":"SV","domain":"","has_mx":false,"reason":"No MX records found"},{"bfs":"SV-131","canton":"Central La Paz","name":"Paraíso de Osorio","provider":"unknown","osm_relation_id":8730034,"population":2607,"district":"","country":"SV","domain":"","has_mx":false,"reason":"No MX records found"},{"bfs":"SV-132","canton":"Northern La Unión","name":"Pasaquina","provider":"unknown","osm_relation_id":8527398,"population":15286,"district":"","country":"SV","domain":"","has_mx":false,"reason":"No MX records found"},{"bfs":"SV-133","canton":"Northern Morazán","name":"Perquín","provider":"unknown","osm_relation_id":19561041,"population":2564,"district":"","country":"SV","domain":"","has_mx":false,"reason":"No MX records found"},{"bfs":"SV-134","canton":"Northern La Unión","name":"Polorós","provider":"unknown","osm_relation_id":19564006,"population":8750,"district":"","country":"SV","domain":"","has_mx":false,"reason":"No MX records found"},{"bfs":"SV-135","canton":"Southern Chalatenango","name":"Potonico","provider":"unknown","osm_relation_id":19563445,"population":1766,"district":"","country":"SV","domain":"","has_mx":false,"reason":"No MX records found"},{"bfs":"SV-136","canton":"Western Usulután","name":"Puerto El Triunfo","provider":"unknown","osm_relation_id":19564004,"population":12983,"district":"","country":"SV","domain":"","has_mx":false,"reason":"No MX records found"},{"bfs":"SV-137","canton":"Southern San Salvador","name":"Rosario de Mora","provider":"unknown","osm_relation_id":13298469,"population":12993,"district":"","country":"SV","domain":"","has_mx":false,"reason":"No MX records found"},{"bfs":"SV-138","canton":"Western La Libertad","name":"Sacacoyo","provider":"unknown","osm_relation_id":19563444,"population":15915,"district":"","country":"SV","domain":"","has_mx":false,"reason":"No MX records found"},{"bfs":"SV-139","canton":"Northern Sonsonate","name":"Salcoatitán","provider":"unknown","osm_relation_id":6955016,"population":7504,"district":"","country":"SV","domain":"","has_mx":false,"reason":"No MX records found"},{"bfs":"SV-140","canton":"Western Usulután","name":"San Agustín","provider":"unknown","osm_relation_id":19564016,"population":5276,"district":"","country":"SV","domain":"","has_mx":false,"reason":"No MX records found"},{"bfs":"SV-141","canton":"Southern La Unión","name":"San Alejo","provider":"unknown","osm_relation_id":8527388,"population":17269,"district":"","country":"SV","domain":"","has_mx":false,"reason":"No MX records found"},{"bfs":"SV-142","canton":"Northern San Miguel","name":"San Antonio","provider":"unknown","osm_relation_id":19560625,"population":5941,"district":"","country":"SV","domain":"","has_mx":false,"reason":"No MX records found"},{"bfs":"SV-143","canton":"Southern Chalatenango","name":"San Antonio Los Ranchos","provider":"unknown","osm_relation_id":19563434,"population":1009,"district":"","country":"SV","domain":"","has_mx":false,"reason":"No MX records found"},{"bfs":"SV-144","canton":"Central La Paz","name":"San Antonio Masahuat","provider":"unknown","osm_relation_id":19563515,"population":3949,"district":"","country":"SV","domain":"","has_mx":false,"reason":"No MX records found"},{"bfs":"SV-145","canton":"Western Santa Ana","name":"San Antonio Pajonal","provider":"unknown","osm_relation_id":6311426,"population":3168,"district":"","country":"SV","domain":"","has_mx":false,"reason":"No MX records found"},{"bfs":"SV-146","canton":"Southern Chalatenango","name":"San Antonio de la Cruz","provider":"unknown","osm_relation_id":19563439,"population":1747,"district":"","country":"SV","domain":"","has_mx":false,"reason":"No MX records found"},{"bfs":"SV-147","canton":"Central Sonsonate","name":"San Antonio del Monte","provider":"unknown","osm_relation_id":13128805,"population":31533,"district":"","country":"SV","domain":"","has_mx":false,"reason":"No MX records found"},{"bfs":"SV-148","canton":"Northern Cuscatlán","name":"San Bartolomé Perulapía","provider":"unknown","osm_relation_id":9222746,"population":7681,"district":"","country":"SV","domain":"","has_mx":false,"reason":"No MX records found"},{"bfs":"SV-149","canton":"Northern Usulután","name":"San Buenaventura","provider":"unknown","osm_relation_id":19564042,"population":5225,"district":"","country":"SV","domain":"","has_mx":false,"reason":"No MX records found"},{"bfs":"SV-150","canton":"Southern Morazán","name":"San Carlos","provider":"unknown","osm_relation_id":8322543,"population":4530,"district":"","country":"SV","domain":"","has_mx":false,"reason":"No MX records found"},{"bfs":"SV-151","canton":"Southern San Vicente","name":"San Cayetano Istepeque","provider":"unknown","osm_relation_id":19560309,"population":4184,"district":"","country":"SV","domain":"","has_mx":false,"reason":"No MX records found"},{"bfs":"SV-152","canton":"Southern Cuscatlán","name":"San Cristóbal","provider":"unknown","osm_relation_id":19563319,"population":9497,"district":"","country":"SV","domain":"","has_mx":false,"reason":"No MX records found"},{"bfs":"SV-153","canton":"Eastern Usulután","name":"San Dionisio","provider":"unknown","osm_relation_id":19564046,"population":3676,"district":"","country":"SV","domain":"","has_mx":false,"reason":"No MX records found"},{"bfs":"SV-154","canton":"Central La Paz","name":"San Emigdio","provider":"unknown","osm_relation_id":19563518,"population":2779,"district":"","country":"SV","domain":"","has_mx":false,"reason":"No MX records found"},{"bfs":"SV-155","canton":"Northern San Vicente","name":"San Esteban Catarina","provider":"unknown","osm_relation_id":19560346,"population":6128,"district":"","country":"SV","domain":"","has_mx":false,"reason":"No MX records found"},{"bfs":"SV-156","canton":"Central Chalatenango","name":"San Fernando","provider":"unknown","osm_relation_id":19560538,"population":2512,"district":"","country":"SV","domain":"","has_mx":false,"reason":"No MX records found"},{"bfs":"SV-157","canton":"Northern Morazán","name":"San Fernando","provider":"unknown","osm_relation_id":19563617,"population":1900,"district":"","country":"SV","domain":"","has_mx":false,"reason":"No MX records found"},{"bfs":"SV-158","canton":"Western La Paz","name":"San Francisco Chinameca","provider":"unknown","osm_relation_id":19563519,"population":7481,"district":"","country":"SV","domain":"","has_mx":false,"reason":"No MX records found"},{"bfs":"SV-159","canton":"Southern Morazán","name":"San Francisco Gotera","provider":"unknown","osm_relation_id":8322749,"population":20330,"district":"","country":"SV","domain":"","has_mx":false,"reason":"No MX records found"},{"bfs":"SV-160","canton":"Western Usulután","name":"San Francisco Javier","provider":"unknown","osm_relation_id":19564053,"population":5144,"district":"","country":"SV","domain":"","has_mx":false,"reason":"No MX records found"},{"bfs":"SV-161","canton":"Southern Chalatenango","name":"San Francisco Lempa","provider":"unknown","osm_relation_id":19560532,"population":774,"district":"","country":"SV","domain":"","has_mx":false,"reason":"No MX records found"},{"bfs":"SV-162","canton":"Southern Ahuachapán","name":"San Francisco Menéndez","provider":"unknown","osm_relation_id":6172096,"population":44906,"district":"","country":"SV","domain":"","has_mx":false,"reason":"No MX records found"},{"bfs":"SV-163","canton":"Central Chalatenango","name":"San Francisco Morazán","provider":"unknown","osm_relation_id":19560529,"population":3036,"district":"","country":"SV","domain":"","has_mx":false,"reason":"No MX records found"},{"bfs":"SV-164","canton":"Northern San Miguel","name":"San Gerardo","provider":"unknown","osm_relation_id":19560641,"population":5644,"district":"","country":"SV","domain":"","has_mx":false,"reason":"No MX records found"},{"bfs":"SV-165","canton":"Northern Chalatenango","name":"San Ignacio","provider":"unknown","osm_relation_id":13284906,"population":9159,"district":"","country":"SV","domain":"","has_mx":false,"reason":"No MX records found"},{"bfs":"SV-166","canton":"Northern San Vicente","name":"San Ildefonso","provider":"unknown","osm_relation_id":19560372,"population":7233,"district":"","country":"SV","domain":"","has_mx":false,"reason":"No MX records found"},{"bfs":"SV-167","canton":"Northern Morazán","name":"San Isidro","provider":"unknown","osm_relation_id":19563651,"population":2811,"district":"","country":"SV","domain":"","has_mx":false,"reason":"No MX records found"},{"bfs":"SV-168","canton":"Eastern Cabañas","name":"San Isidro","provider":"unknown","osm_relation_id":19560462,"population":7333,"district":"","country":"SV","domain":"","has_mx":false,"reason":"No MX records found"},{"bfs":"SV-169","canton":"Southern Chalatenango","name":"San Isidro Labrador","provider":"unknown","osm_relation_id":19564347,"population":586,"district":"","country":"SV","domain":"","has_mx":false,"reason":"No MX records found"},{"bfs":"SV-170","canton":"Western San Miguel","name":"San Jorge","provider":"unknown","osm_relation_id":19560659,"population":9414,"district":"","country":"SV","domain":"","has_mx":false,"reason":"No MX records found"},{"bfs":"SV-171","canton":"Northern La Unión","name":"San José","provider":"unknown","osm_relation_id":19564015,"population":2544,"district":"","country":"SV","domain":"","has_mx":false,"reason":"No MX records found"},{"bfs":"SV-172","canton":"Southern Chalatenango","name":"San José Cancasque","provider":"unknown","osm_relation_id":19563810,"population":1907,"district":"","country":"SV","domain":"","has_mx":false,"reason":"No MX records found"},{"bfs":"SV-173","canton":"Northern Cuscatlán","name":"San José Guayabal","provider":"unknown","osm_relation_id":9222324,"population":14032,"district":"","country":"SV","domain":"","has_mx":false,"reason":"No MX records found"},{"bfs":"SV-174","canton":"Eastern La Libertad","name":"San José Villanueva","provider":"unknown","osm_relation_id":19563446,"population":19150,"district":"","country":"SV","domain":"","has_mx":false,"reason":"No MX records found"},{"bfs":"SV-175","canton":"Eastern La Paz","name":"San Juan Nonualco","provider":"unknown","osm_relation_id":8418051,"population":18068,"district":"","country":"SV","domain":"","has_mx":false,"reason":"No MX records found"},{"bfs":"SV-176","canton":"Central La Libertad","name":"San Juan Opico","provider":"unknown","osm_relation_id":6575978,"population":97210,"district":"","country":"SV","domain":"","has_mx":false,"reason":"No MX records found"},{"bfs":"SV-177","canton":"Western La Paz","name":"San Juan Talpa","provider":"unknown","osm_relation_id":8729910,"population":7666,"district":"","country":"SV","domain":"","has_mx":false,"reason":"No MX records found"},{"bfs":"SV-178","canton":"Central La Paz","name":"San Juan Tepezontes","provider":"unknown","osm_relation_id":19563529,"population":3758,"district":"","country":"SV","domain":"","has_mx":false,"reason":"No MX records found"},{"bfs":"SV-179","canton":"Eastern Sonsonate","name":"San Julián","provider":"unknown","osm_relation_id":7922757,"population":19591,"district":"","country":"SV","domain":"","has_mx":false,"reason":"No MX records found"},{"bfs":"SV-180","canton":"Northern Ahuachapán","name":"San Lorenzo","provider":"unknown","osm_relation_id":9395435,"population":11132,"district":"","country":"SV","domain":"","has_mx":false,"reason":"No MX records found"},{"bfs":"SV-181","canton":"Northern San Vicente","name":"San Lorenzo","provider":"unknown","osm_relation_id":19560397,"population":5144,"district":"","country":"SV","domain":"","has_mx":false,"reason":"No MX records found"},{"bfs":"SV-182","canton":"Central La Paz","name":"San Luis La Herradura","provider":"unknown","osm_relation_id":6594235,"population":20542,"district":"","country":"SV","domain":"","has_mx":false,"reason":"No MX records found"},{"bfs":"SV-183","canton":"Western La Paz","name":"San Luis Talpa","provider":"unknown","osm_relation_id":8551728,"population":24036,"district":"","country":"SV","domain":"","has_mx":false,"reason":"No MX records found"},{"bfs":"SV-184","canton":"Northern San Miguel","name":"San Luis de la Reina","provider":"unknown","osm_relation_id":19560654,"population":5561,"district":"","country":"SV","domain":"","has_mx":false,"reason":"No MX records found"},{"bfs":"SV-185","canton":"Southern Chalatenango","name":"San Luis del Carmen","provider":"unknown","osm_relation_id":19560485,"population":1038,"district":"","country":"SV","domain":"","has_mx":false,"reason":"No MX records found"},{"bfs":"SV-186","canton":"Southern San Salvador","name":"San Marcos","provider":"local-isp","osm_relation_id":6487125,"population":57094,"district":"","country":"SV","isp_name":"OVH (FR)","mx_countries":["CA"],"domain":"sansalvadorsur.gob.sv","has_mx":true,"mx":["sansalvadorsur.gob.sv"],"reason":"MX (sansalvadorsur.gob.sv) hosted on Local ISP (OVH (FR))","spf":"v=spf1 +a +mx +ip4:51.79.72.49 ~all","autodiscover":{"autodiscover_srv":"cpanelemaildiscovery.cpanel.net"}},{"bfs":"SV-187","canton":"Eastern San Salvador","name":"San Martín","provider":"unknown","osm_relation_id":8113619,"population":87931,"district":"","country":"SV","domain":"","has_mx":false,"reason":"No MX records found"},{"bfs":"SV-188","canton":"Northern La Libertad","name":"San Matías","provider":"unknown","osm_relation_id":6669092,"population":7074,"district":"","country":"SV","domain":"","has_mx":false,"reason":"No MX records found"},{"bfs":"SV-189","canton":"Central San Miguel","name":"San Miguel","provider":"independent","osm_relation_id":19560713,"population":232887,"district":"","country":"SV","mx_countries":["DE"],"domain":"sanmiguel.gob.sv","has_mx":true,"mx":["sanmiguel.gob.sv"],"reason":"MX (sanmiguel.gob.sv) is self-hosted","spf":"v=spf1 +a +mx +ip4:5.189.176.210 ~all","autodiscover":{"autodiscover_srv":"cpanelemaildiscovery.cpanel.net"}},{"bfs":"SV-190","canton":"Central La Paz","name":"San Miguel Tepezontes","provider":"unknown","osm_relation_id":19563540,"population":5594,"district":"","country":"SV","domain":"","has_mx":false,"reason":"No MX records found"},{"bfs":"SV-191","canton":"Southern Chalatenango","name":"San Miguel de Mercedes","provider":"unknown","osm_relation_id":19560456,"population":2492,"district":"","country":"SV","domain":"","has_mx":false,"reason":"No MX records found"},{"bfs":"SV-192","canton":"Northern La Libertad","name":"San Pablo Tacachico","provider":"unknown","osm_relation_id":6669083,"population":18710,"district":"","country":"SV","domain":"","has_mx":false,"reason":"No MX records found"},{"bfs":"SV-193","canton":"Western La Paz","name":"San Pedro Masahuat","provider":"unknown","osm_relation_id":19563580,"population":28512,"district":"","country":"SV","domain":"","has_mx":false,"reason":"No MX records found"},{"bfs":"SV-194","canton":"Central La Paz","name":"San Pedro Nonualco","provider":"unknown","osm_relation_id":8592737,"population":9443,"district":"","country":"SV","domain":"","has_mx":false,"reason":"No MX records found"},{"bfs":"SV-195","canton":"Northern Cuscatlán","name":"San Pedro Perulapán","provider":"unknown","osm_relation_id":19563341,"population":51414,"district":"","country":"SV","domain":"","has_mx":false,"reason":"No MX records found"},{"bfs":"SV-196","canton":"Southern Ahuachapán","name":"San Pedro Puxtla","provider":"unknown","osm_relation_id":6626627,"population":8749,"district":"","country":"SV","domain":"","has_mx":false,"reason":"No MX records found"},{"bfs":"SV-197","canton":"Central Chalatenango","name":"San Rafael","provider":"unknown","osm_relation_id":19560447,"population":3964,"district":"","country":"SV","domain":"","has_mx":false,"reason":"No MX records found"},{"bfs":"SV-198","canton":"Southern Cuscatlán","name":"San Rafael Cedros","provider":"unknown","osm_relation_id":19563345,"population":16303,"district":"","country":"SV","domain":"","has_mx":false,"reason":"No MX records found"},{"bfs":"SV-199","canton":"Eastern La Paz","name":"San Rafael Obrajuelo","provider":"unknown","osm_relation_id":19563583,"population":9566,"district":"","country":"SV","domain":"","has_mx":false,"reason":"No MX records found"},{"bfs":"SV-200","canton":"Western San Miguel","name":"San Rafael Oriente","provider":"unknown","osm_relation_id":19560721,"population":11958,"district":"","country":"SV","domain":"","has_mx":false,"reason":"No MX records found"},{"bfs":"SV-201","canton":"Southern Cuscatlán","name":"San Ramón","provider":"unknown","osm_relation_id":9222765,"population":6516,"district":"","country":"SV","domain":"","has_mx":false,"reason":"No MX records found"},{"bfs":"SV-202","canton":"Central San Salvador","name":"San Salvador","provider":"independent","osm_relation_id":6462027,"population":330543,"district":"","country":"SV","mx_countries":["SV"],"domain":"sansalvador.gob.sv","has_mx":true,"mx":["mail.sansalvador.gob.sv"],"reason":"MX (mail.sansalvador.gob.sv) is self-hosted","spf":"v=spf1 a:mail.sansalvador.gob.sv mx ip4:168.243.210.13 -all"},{"bfs":"SV-203","canton":"Northern San Vicente","name":"San Sebastián","provider":"unknown","osm_relation_id":19560415,"population":12781,"district":"","country":"SV","domain":"","has_mx":false,"reason":"No MX records found"},{"bfs":"SV-204","canton":"Western Santa Ana","name":"San Sebastián Salitrillo","provider":"unknown","osm_relation_id":6094976,"population":30004,"district":"","country":"SV","domain":"","has_mx":false,"reason":"No MX records found"},{"bfs":"SV-205","canton":"Southern Morazán","name":"San Simón","provider":"unknown","osm_relation_id":19563793,"population":11205,"district":"","country":"SV","domain":"","has_mx":false,"reason":"No MX records found"},{"bfs":"SV-206","canton":"Southern San Vicente","name":"San Vicente","provider":"unknown","osm_relation_id":19560481,"population":52461,"district":"","country":"SV","domain":"","has_mx":false,"reason":"No MX records found"},{"bfs":"SV-207","canton":"Central Santa Ana","name":"Santa Ana","provider":"microsoft","osm_relation_id":5901411,"population":250760,"district":"","country":"SV","mx_countries":["US"],"domain":"santaana.gob.sv","has_mx":true,"mx":["santaana-gob-sv.mail.protection.outlook.com"],"reason":"MX record (santaana-gob-sv.mail.protection.outlook.com) matches Microsoft","spf":"v=spf1 include:spf.protection.outlook.com -all","autodiscover":{"autodiscover_cname":"autodiscover.outlook.com"},"txt_verifications":{"microsoft":"ms85058804","google":"lzh2Uy7UwJX0xbH2LfVinZbdGSxCRiv_hn1eXP68F6g"}},{"bfs":"SV-208","canton":"Northern Sonsonate","name":"Santa Catarina Masahuat","provider":"unknown","osm_relation_id":13128730,"population":12067,"district":"","country":"SV","domain":"","has_mx":false,"reason":"No MX records found"},{"bfs":"SV-209","canton":"Northern San Vicente","name":"Santa Clara","provider":"unknown","osm_relation_id":19560496,"population":5214,"district":"","country":"SV","domain":"","has_mx":false,"reason":"No MX records found"},{"bfs":"SV-210","canton":"Southern Cuscatlán","name":"Santa Cruz Analquito","provider":"unknown","osm_relation_id":8022699,"population":2409,"district":"","country":"SV","domain":"","has_mx":false,"reason":"No MX records found"},{"bfs":"SV-211","canton":"Southern Cuscatlán","name":"Santa Cruz Michapa","provider":"unknown","osm_relation_id":19563354,"population":13893,"district":"","country":"SV","domain":"","has_mx":false,"reason":"No MX records found"},{"bfs":"SV-212","canton":"Eastern Usulután","name":"Santa Elena","provider":"unknown","osm_relation_id":19564062,"population":16051,"district":"","country":"SV","domain":"","has_mx":false,"reason":"No MX records found"},{"bfs":"SV-213","canton":"Eastern Sonsonate","name":"Santa Isabel Ishuatán","provider":"unknown","osm_relation_id":6832812,"population":10313,"district":"","country":"SV","domain":"","has_mx":false,"reason":"No MX records found"},{"bfs":"SV-214","canton":"Eastern Usulután","name":"Santa María","provider":"unknown","osm_relation_id":19564066,"population":12780,"district":"","country":"SV","domain":"","has_mx":false,"reason":"No MX records found"},{"bfs":"SV-215","canton":"Central La Paz","name":"Santa María Ostuma","provider":"unknown","osm_relation_id":8729975,"population":5853,"district":"","country":"SV","domain":"","has_mx":false,"reason":"No MX records found"},{"bfs":"SV-216","canton":"Central Chalatenango","name":"Santa Rita","provider":"unknown","osm_relation_id":19560436,"population":4298,"district":"","country":"SV","domain":"","has_mx":false,"reason":"No MX records found"},{"bfs":"SV-217","canton":"Northern Santa Ana","name":"Santa Rosa Guachipilín","provider":"unknown","osm_relation_id":6525316,"population":4260,"district":"","country":"SV","domain":"","has_mx":false,"reason":"No MX records found"},{"bfs":"SV-218","canton":"Northern La Unión","name":"Santa Rosa de Lima","provider":"unknown","osm_relation_id":19564018,"population":28350,"district":"","country":"SV","domain":"","has_mx":false,"reason":"No MX records found"},{"bfs":"SV-219","canton":"Southern La Libertad","name":"Santa Tecla","provider":"google","osm_relation_id":8705400,"population":125532,"district":"","country":"SV","mx_countries":["US"],"domain":"lalibertadsur.gob.sv","has_mx":true,"mx":["smtp.google.com"],"reason":"MX record (smtp.google.com) matches Google","spf":"v=spf1 include:_spf.google.com ~all","txt_verifications":{"google":"WAbmEV5r2sYHxm9uhQkU3N0OxMQ4aqbrj-FuXqilRo4"}},{"bfs":"SV-220","canton":"Central La Paz","name":"Santiago Nonualco","provider":"unknown","osm_relation_id":19563614,"population":42254,"district":"","country":"SV","domain":"","has_mx":false,"reason":"No MX records found"},{"bfs":"SV-221","canton":"Southern San Salvador","name":"Santiago Texacuangos","provider":"unknown","osm_relation_id":8147940,"population":20081,"district":"","country":"SV","domain":"","has_mx":false,"reason":"No MX records found"},{"bfs":"SV-222","canton":"Northern Usulután","name":"Santiago de María","provider":"unknown","osm_relation_id":19564069,"population":17940,"district":"","country":"SV","domain":"","has_mx":false,"reason":"No MX records found"},{"bfs":"SV-223","canton":"Western Santa Ana","name":"Santiago de la Frontera","provider":"unknown","osm_relation_id":8527319,"population":5017,"district":"","country":"SV","domain":"","has_mx":false,"reason":"No MX records found"},{"bfs":"SV-224","canton":"Northern San Vicente","name":"Santo Domingo","provider":"unknown","osm_relation_id":19560505,"population":6467,"district":"","country":"SV","domain":"","has_mx":false,"reason":"No MX records found"},{"bfs":"SV-225","canton":"Central Sonsonate","name":"Santo Domingo de Guzmán","provider":"unknown","osm_relation_id":13128734,"population":7291,"district":"","country":"SV","domain":"","has_mx":false,"reason":"No MX records found"},{"bfs":"SV-226","canton":"Southern San Salvador","name":"Santo Tomás","provider":"unknown","osm_relation_id":8147932,"population":32099,"district":"","country":"SV","domain":"","has_mx":false,"reason":"No MX records found"},{"bfs":"SV-227","canton":"Southern Morazán","name":"Sensembra","provider":"unknown","osm_relation_id":19563809,"population":2602,"district":"","country":"SV","domain":"","has_mx":false,"reason":"No MX records found"},{"bfs":"SV-228","canton":"Eastern Cabañas","name":"Sensuntepeque","provider":"unknown","osm_relation_id":19560495,"population":35916,"district":"","country":"SV","domain":"","has_mx":false,"reason":"No MX records found"},{"bfs":"SV-229","canton":"Northern San Miguel","name":"Sesori","provider":"unknown","osm_relation_id":19560734,"population":10128,"district":"","country":"SV","domain":"","has_mx":false,"reason":"No MX records found"},{"bfs":"SV-230","canton":"Southern Morazán","name":"Sociedad","provider":"unknown","osm_relation_id":19563906,"population":9963,"district":"","country":"SV","domain":"","has_mx":false,"reason":"No MX records found"},{"bfs":"SV-231","canton":"Central Sonsonate","name":"Sonsonate","provider":"microsoft","osm_relation_id":13128797,"population":72233,"district":"","country":"SV","mx_countries":["US"],"domain":"alcaldiadesonsonate.gob.sv","has_mx":true,"mx":["alcaldiadesonsonate-gob-sv.mail.protection.outlook.com"],"reason":"MX record (alcaldiadesonsonate-gob-sv.mail.protection.outlook.com) matches Microsoft","spf":"v=spf1 ip4:15.235.65.124 ip4:107.155.106.18 +ip4:23.111.161.94 +include:spf.protection.outlook.com ~all","autodiscover":{"autodiscover_cname":"autodiscover.outlook.com","autodiscover_srv":"cpanelemaildiscovery.cpanel.net"}},{"bfs":"SV-232","canton":"Central Sonsonate","name":"Sonzacate","provider":"unknown","osm_relation_id":13128820,"population":28226,"district":"","country":"SV","domain":"","has_mx":false,"reason":"No MX records found"},{"bfs":"SV-233","canton":"Eastern San Salvador","name":"Soyapango","provider":"unknown","osm_relation_id":8148131,"population":230255,"district":"","country":"SV","domain":"alcaldiasansalvadoreste.gob.sv","has_mx":false,"reason":"No MX records found"},{"bfs":"SV-234","canton":"Northern Cuscatlán","name":"Suchitoto","provider":"unknown","osm_relation_id":9222262,"population":22716,"district":"","country":"SV","domain":"","has_mx":false,"reason":"No MX records found"},{"bfs":"SV-235","canton":"Central Ahuachapán","name":"Tacuba","provider":"unknown","osm_relation_id":6172141,"population":31208,"district":"","country":"SV","domain":"","has_mx":false,"reason":"No MX records found"},{"bfs":"SV-236","canton":"Western La Libertad","name":"Talnique","provider":"unknown","osm_relation_id":19563447,"population":5596,"district":"","country":"SV","domain":"","has_mx":false,"reason":"No MX records found"},{"bfs":"SV-237","canton":"Coastal La Libertad","name":"Tamanique","provider":"google","gateway":"jellyfish","osm_relation_id":7369200,"population":14068,"district":"","country":"SV","mx_countries":["US"],"domain":"tamanique.gob.sv","has_mx":true,"mx":["mx1-hosting.jellyfish.systems","mx2-hosting.jellyfish.systems","mx3-hosting.jellyfish.systems"],"reason":"MX is jellyfish gateway; TXT verification proves google tenant","spf":"v=spf1 +a +mx +ip4:162.0.232.136 include:spf.web-hosting.com ~all","autodiscover":{"autodiscover_srv":"cpanelemaildiscovery.cpanel.net"},"txt_verifications":{"google":"BLi-n-B7kMtpqniGlk1_VmovaWkNje0yNf68sFTIgW0"}},{"bfs":"SV-238","canton":"Western La Paz","name":"Tapalhuaca","provider":"unknown","osm_relation_id":19563618,"population":3711,"district":"","country":"SV","domain":"","has_mx":false,"reason":"No MX records found"},{"bfs":"SV-239","canton":"Eastern Usulután","name":"Tecapán","provider":"unknown","osm_relation_id":19564074,"population":7369,"district":"","country":"SV","domain":"","has_mx":false,"reason":"No MX records found"},{"bfs":"SV-240","canton":"Southern San Vicente","name":"Tecoluca","provider":"unknown","osm_relation_id":19560518,"population":26656,"district":"","country":"SV","domain":"","has_mx":false,"reason":"No MX records found"},{"bfs":"SV-241","canton":"Western Cabañas","name":"Tejutepeque","provider":"unknown","osm_relation_id":19560504,"population":7189,"district":"","country":"SV","domain":"","has_mx":false,"reason":"No MX records found"},{"bfs":"SV-242","canton":"Central Chalatenango","name":"Tejutla","provider":"unknown","osm_relation_id":19560399,"population":13556,"district":"","country":"SV","domain":"","has_mx":false,"reason":"No MX records found"},{"bfs":"SV-243","canton":"Southern Cuscatlán","name":"Tenancingo","provider":"unknown","osm_relation_id":19563369,"population":6707,"district":"","country":"SV","domain":"","has_mx":false,"reason":"No MX records found"},{"bfs":"SV-244","canton":"Coastal La Libertad","name":"Teotepeque","provider":"unknown","osm_relation_id":6637187,"population":9862,"district":"","country":"SV","domain":"","has_mx":false,"reason":"No MX records found"},{"bfs":"SV-245","canton":"Western La Libertad","name":"Tepecoyo","provider":"unknown","osm_relation_id":7369464,"population":14097,"district":"","country":"SV","domain":"","has_mx":false,"reason":"No MX records found"},{"bfs":"SV-246","canton":"Southern San Vicente","name":"Tepetitán","provider":"unknown","osm_relation_id":19560531,"population":3869,"district":"","country":"SV","domain":"","has_mx":false,"reason":"No MX records found"},{"bfs":"SV-247","canton":"Northern Santa Ana","name":"Texistepeque","provider":"unknown","osm_relation_id":8527293,"population":19271,"district":"","country":"SV","domain":"","has_mx":false,"reason":"No MX records found"},{"bfs":"SV-248","canton":"Eastern San Salvador","name":"Tonacatepeque","provider":"unknown","osm_relation_id":9229437,"population":89751,"district":"","country":"SV","domain":"","has_mx":false,"reason":"No MX records found"},{"bfs":"SV-249","canton":"Northern Morazán","name":"Torola","provider":"unknown","osm_relation_id":19563912,"population":3082,"district":"","country":"SV","domain":"","has_mx":false,"reason":"No MX records found"},{"bfs":"SV-250","canton":"Northern Ahuachapán","name":"Turín","provider":"unknown","osm_relation_id":6744519,"population":10122,"district":"","country":"SV","domain":"","has_mx":false,"reason":"No MX records found"},{"bfs":"SV-251","canton":"Central San Miguel","name":"Uluazapa","provider":"unknown","osm_relation_id":19560737,"population":3339,"district":"","country":"SV","domain":"","has_mx":false,"reason":"No MX records found"},{"bfs":"SV-252","canton":"Eastern Usulután","name":"Usulután","provider":"independent","osm_relation_id":19566995,"population":66125,"district":"","country":"SV","mx_countries":["US"],"domain":"usulutan.gob.sv","has_mx":true,"mx":["mx1.privateemail.com","mx2.privateemail.com"],"reason":"MX (mx1.privateemail.com, mx2.privateemail.com) is self-hosted","spf":"v=spf1 ip4:203.161.53.132 ip4:192.40.115.126 ip4:192.40.115.10 +include:spf.privateemail.com ~all","autodiscover":{"autodiscover_cname":"privateemail.com"},"txt_verifications":{"microsoft":"ms21306207"}},{"bfs":"SV-253","canton":"Southern San Vicente","name":"Verapaz","provider":"unknown","osm_relation_id":19560536,"population":6223,"district":"","country":"SV","domain":"","has_mx":false,"reason":"No MX records found"},{"bfs":"SV-254","canton":"Eastern Cabañas","name":"Victoria","provider":"unknown","osm_relation_id":19560526,"population":10953,"district":"","country":"SV","domain":"","has_mx":false,"reason":"No MX records found"},{"bfs":"SV-255","canton":"Southern Morazán","name":"Yamabal","provider":"unknown","osm_relation_id":19564005,"population":3010,"district":"","country":"SV","domain":"","has_mx":false,"reason":"No MX records found"},{"bfs":"SV-256","canton":"Southern La Unión","name":"Yayantique","provider":"unknown","osm_relation_id":8283266,"population":5847,"district":"","country":"SV","domain":"","has_mx":false,"reason":"No MX records found"},{"bfs":"SV-257","canton":"Southern Morazán","name":"Yoloaiquín","provider":"unknown","osm_relation_id":19560316,"population":3142,"district":"","country":"SV","domain":"","has_mx":false,"reason":"No MX records found"},{"bfs":"SV-258","canton":"Southern La Unión","name":"Yucuaiquín","provider":"unknown","osm_relation_id":8527399,"population":6141,"district":"","country":"SV","domain":"","has_mx":false,"reason":"No MX records found"},{"bfs":"SV-259","canton":"Eastern La Paz","name":"Zacatecoluca","provider":"unknown","osm_relation_id":8434190,"population":64484,"district":"","country":"SV","domain":"","has_mx":false,"reason":"No MX records found"},{"bfs":"SV-260","canton":"Eastern La Libertad","name":"Zaragoza","provider":"independent","osm_relation_id":19563470,"population":26510,"district":"","country":"SV","mx_countries":["US"],"domain":"zaragoza.gob.sv","has_mx":true,"mx":["mail.zaragoza.gob.sv"],"reason":"MX (mail.zaragoza.gob.sv) is self-hosted","spf":"v=spf1 ip4:209.188.21.92 +a +mx include:spf.antispamcloud.com ~all","autodiscover":{"autodiscover_srv":"cpanelemaildiscovery.cpanel.net"}}]