[{"country":"TJ","canton":"Sughd Province","osm_relation_id":3280682,"domain":"","population":176300,"name":"Asht District","bfs":"TJ-001","district":"","provider":"unknown","has_mx":false,"reason":"No MX records found"},{"country":"TJ","canton":"Sughd Province","osm_relation_id":3280692,"domain":"ayni.tj","population":91200,"name":"Ayni District","bfs":"TJ-002","mx_countries":["RU"],"district":"","provider":"independent","has_mx":true,"mx":["mx1.timeweb.ru","mx2.timeweb.ru"],"reason":"MX (mx1.timeweb.ru, mx2.timeweb.ru) is self-hosted","autodiscover":{"autodiscover_srv":"cpanelemaildiscovery.cpanel.net"}},{"country":"TJ","canton":"Khatlon Province","osm_relation_id":3281963,"domain":"","population":32700,"name":"Baljuvon District","bfs":"TJ-003","district":"","provider":"unknown","has_mx":false,"reason":"No MX records found"},{"country":"TJ","canton":"Tajik Soviet Socialist Republic","osm_relation_id":3281965,"domain":"","population":171900,"name":"Danghara District","bfs":"TJ-004","district":"","provider":"unknown","has_mx":false,"reason":"No MX records found"},{"country":"TJ","canton":"Gorno-Badakhshan Autonomous Region","osm_relation_id":3281969,"domain":"","population":23700,"name":"Darvoz District","bfs":"TJ-005","district":"","provider":"unknown","has_mx":false,"reason":"No MX records found"},{"country":"TJ","canton":"Sughd Province","osm_relation_id":3280690,"domain":"devashtich.tj","population":166700,"name":"Devashtich District","bfs":"TJ-006","mx_countries":["TJ"],"district":"","provider":"independent","has_mx":true,"mx":["mail.devashtich.tj"],"reason":"MX (mail.devashtich.tj) is self-hosted"},{"country":"TJ","canton":"Khatlon Province","domain":"","population":122000,"name":"Dusti District","bfs":"TJ-007","district":"","provider":"unknown","has_mx":false,"reason":"No MX records found"},{"country":"TJ","canton":"Khatlon Province","osm_relation_id":3281941,"domain":"","population":183900,"name":"Dzhami District","bfs":"TJ-008","district":"","provider":"unknown","has_mx":false,"reason":"No MX records found"},{"country":"TJ","canton":"Districts under Central Government Jurisdiction","osm_relation_id":3281936,"domain":"faizobod.tj","population":111700,"name":"Faizobod District","bfs":"TJ-009","mx_countries":["TJ"],"district":"","provider":"independent","has_mx":true,"mx":["mail.faizobod.tj"],"reason":"MX (mail.faizobod.tj) is self-hosted"},{"country":"TJ","canton":"Khatlon Province","osm_relation_id":3281966,"domain":"","population":179100,"name":"Farkhor District","bfs":"TJ-010","district":"","provider":"unknown","has_mx":false,"reason":"No MX records found"},{"country":"TJ","canton":"Sughd Province","osm_relation_id":3280693,"domain":"","population":388600,"name":"Ghafurov District","bfs":"TJ-011","district":"","provider":"unknown","has_mx":false,"reason":"No MX records found"},{"country":"TJ","canton":"Khatlon Province","osm_relation_id":3281951,"domain":"hamadoni.tj","population":154300,"name":"Hamadoni District","bfs":"TJ-012","mx_countries":["TJ"],"district":"","provider":"independent","has_mx":true,"mx":["mail.hamadoni.tj"],"reason":"MX (mail.hamadoni.tj) is self-hosted"},{"country":"TJ","canton":"Districts under Central Government Jurisdiction","osm_relation_id":3281935,"domain":"","population":331400,"name":"Hisar District","bfs":"TJ-013","district":"","provider":"unknown","has_mx":false,"reason":"No MX records found"},{"country":"TJ","canton":"Sughd Province","osm_relation_id":3280683,"domain":"isfara.tj","population":285000,"name":"Isfara District","bfs":"TJ-014","mx_countries":["TJ"],"district":"","provider":"independent","has_mx":true,"mx":["mail.isfara.tj"],"reason":"MX (mail.isfara.tj) is self-hosted"},{"country":"TJ","canton":"Gorno-Badakhshan Autonomous Region","osm_relation_id":3281971,"domain":"","population":32700,"name":"Ishkoshim District","bfs":"TJ-015","district":"","provider":"unknown","has_mx":false,"reason":"No MX records found"},{"country":"TJ","canton":"Sughd Province","osm_relation_id":3281013,"domain":"sugd.tj","population":288100,"name":"Istaravshan District","bfs":"TJ-016","mx_countries":["TJ"],"district":"","provider":"independent","has_mx":true,"mx":["mail.sugd.tj"],"reason":"MX (mail.sugd.tj) is self-hosted","spf":"v=spf1 +a +mx +ip4:193.111.11.11 ~all","autodiscover":{"autodiscover_srv":"cpanelemaildiscovery.cpanel.net"}},{"country":"TJ","canton":"Sughd Province","osm_relation_id":3281014,"domain":"","population":144100,"name":"Jabbor Rasulov District","bfs":"TJ-017","district":"","provider":"unknown","has_mx":false,"reason":"No MX records found"},{"country":"TJ","canton":"Khatlon Province","domain":"balkhi.tj","population":181900,"name":"Jaloliddin Balkhi District","bfs":"TJ-018","mx_countries":["TJ"],"district":"","provider":"independent","has_mx":true,"mx":["mail.balkhi.tj","mail.balkhi.tj"],"reason":"MX (mail.balkhi.tj, mail.balkhi.tj) is self-hosted","autodiscover":{"autodiscover_srv":"cpanelemaildiscovery.cpanel.net"}},{"country":"TJ","canton":"Khatlon Province","osm_relation_id":3281946,"domain":"","population":145600,"name":"Jayhun District","bfs":"TJ-019","district":"","provider":"unknown","has_mx":false,"reason":"No MX records found"},{"country":"TJ","canton":"Khatlon Province","osm_relation_id":3281962,"domain":"khovaling.tj","population":58300,"name":"Khovaling District","bfs":"TJ-020","mx_countries":["TJ"],"district":"","provider":"independent","has_mx":true,"mx":["mail.khovaling.tj"],"reason":"MX (mail.khovaling.tj) is self-hosted"},{"country":"TJ","canton":"Khatlon Province","osm_relation_id":3281945,"domain":"khuroson.tj","population":116500,"name":"Khuroson District","bfs":"TJ-021","mx_countries":["TJ"],"district":"","provider":"independent","has_mx":true,"mx":["mail.khuroson.tj"],"reason":"MX (mail.khuroson.tj) is self-hosted"},{"country":"TJ","canton":"Sughd Province","osm_relation_id":3280684,"domain":"konibodom.tj","population":219900,"name":"Konibodom District","bfs":"TJ-022","mx_countries":["RU"],"district":"","provider":"independent","has_mx":true,"mx":["mx1.beget.com","mx2.beget.com"],"reason":"MX (mx1.beget.com, mx2.beget.com) is self-hosted","spf":"v=spf1 redirect=beget.com","autodiscover":{"autodiscover_cname":"autoconfig.beget.com"}},{"country":"TJ","canton":"Sughd Province","osm_relation_id":3280686,"domain":"","population":24400,"name":"Kuhistoni Mastchoh District","bfs":"TJ-023","district":"","provider":"unknown","has_mx":false,"reason":"No MX records found"},{"country":"TJ","canton":"Tajik Soviet Socialist Republic","osm_relation_id":3281947,"domain":"kulob.tj","population":96000,"name":"Kulob District","bfs":"TJ-024","mx_countries":["TJ"],"district":"","provider":"independent","has_mx":true,"mx":["mail.kulob.tj"],"reason":"MX (mail.kulob.tj) is self-hosted"},{"country":"TJ","canton":"Khatlon Province","osm_relation_id":3281954,"domain":"kushoniyon.tj","population":224600,"name":"Kushoniyon District","bfs":"TJ-025","mx_countries":["TJ"],"district":"","provider":"independent","has_mx":true,"mx":["mail.kushoniyon.tj"],"reason":"MX (mail.kushoniyon.tj) is self-hosted"},{"country":"TJ","canton":"Districts under Central Government Jurisdiction","osm_relation_id":3281957,"domain":"lakhsh.tj","population":54400,"name":"Lakhsh District","bfs":"TJ-026","mx_countries":["TJ"],"district":"","provider":"independent","has_mx":true,"mx":["mail.tajnet.tj"],"reason":"MX (mail.tajnet.tj) is self-hosted","spf":"v=spf1 +a +mx include:_spf.google.com -all"},{"country":"TJ","canton":"Sughd Province","osm_relation_id":3280691,"domain":"","population":150700,"name":"Mastchoh District","bfs":"TJ-027","district":"","provider":"unknown","has_mx":false,"reason":"No MX records found"},{"country":"TJ","canton":"Khatlon Province","osm_relation_id":3281938,"domain":"muminobod.tj","population":99300,"name":"Muminobod District","bfs":"TJ-028","mx_countries":["RU"],"district":"","provider":"independent","has_mx":true,"mx":["mail.muminobod.tj","mail.muminobod.tj"],"reason":"MX (mail.muminobod.tj, mail.muminobod.tj) is self-hosted","spf":"v=spf1 ip4:185.200.240.65 a mx ~all"},{"country":"TJ","canton":"Gorno-Badakhshan Autonomous Region","osm_relation_id":3281933,"domain":"","population":16500,"name":"Murghob District","bfs":"TJ-029","district":"","provider":"unknown","has_mx":false,"reason":"No MX records found"},{"country":"TJ","canton":"Khatlon Province","osm_relation_id":3281959,"domain":"norak.tj","population":64900,"name":"Norak District","bfs":"TJ-030","mx_countries":["TJ"],"district":"","provider":"independent","has_mx":true,"mx":["mail.norak.tj","mail.norak.tj"],"reason":"MX (mail.norak.tj, mail.norak.tj) is self-hosted","spf":"v=spf1 +a +mx +ip4:193.111.11.11 ~all"},{"country":"TJ","canton":"Khatlon Province","osm_relation_id":3281932,"domain":"","population":45100,"name":"Nosiri Khusrav District","bfs":"TJ-031","district":"","provider":"unknown","has_mx":false,"reason":"No MX records found"},{"country":"TJ","canton":"Tajikistan","osm_relation_id":3281949,"domain":"nurobod.tj","population":74200,"name":"Nurobod District","bfs":"TJ-032","mx_countries":["TJ"],"district":"","provider":"independent","has_mx":true,"mx":["mail.nurobod.tj"],"reason":"MX (mail.nurobod.tj) is self-hosted"},{"country":"TJ","canton":"Tajik Soviet Socialist Republic","osm_relation_id":3281958,"domain":"","population":104900,"name":"Panj District","bfs":"TJ-033","district":"","provider":"unknown","has_mx":false,"reason":"No MX records found"},{"country":"TJ","canton":"Sughd Province","osm_relation_id":3280687,"domain":"","population":312400,"name":"Panjakent District","bfs":"TJ-034","district":"","provider":"unknown","has_mx":false,"reason":"No MX records found"},{"country":"TJ","canton":"Districts under Central Government Jurisdiction","osm_relation_id":3281968,"domain":"rasht.tj","population":137328,"name":"Rasht District","bfs":"TJ-035","mx_countries":["TJ"],"district":"","provider":"independent","has_mx":true,"mx":["mail.rasht.tj"],"reason":"MX (mail.rasht.tj) is self-hosted"},{"country":"TJ","canton":"Districts under Central Government Jurisdiction","osm_relation_id":3281937,"domain":"roghun.tj","population":42600,"name":"Roghun District","bfs":"TJ-036","mx_countries":["TJ"],"district":"","provider":"independent","has_mx":true,"mx":["mail.roghun.tj"],"reason":"MX (mail.roghun.tj) is self-hosted"},{"country":"TJ","canton":"Gorno-Badakhshan Autonomous Region","osm_relation_id":3281930,"domain":"roshtqala.tj","population":27200,"name":"Roshtqal'a District","bfs":"TJ-037","mx_countries":["RU"],"district":"","provider":"independent","has_mx":true,"mx":["mx1.beget.com","mx2.beget.com"],"reason":"MX (mx1.beget.com, mx2.beget.com) is self-hosted","spf":"v=spf1 redirect=beget.com","autodiscover":{"autodiscover_cname":"autoconfig.beget.com"}},{"country":"TJ","canton":"Tajikistan","osm_relation_id":3281973,"domain":"","population":387200,"name":"Rudaki District","bfs":"TJ-038","district":"","provider":"unknown","has_mx":false,"reason":"No MX records found"},{"country":"TJ","canton":"Gorno-Badakhshan Autonomous Region","osm_relation_id":3281942,"domain":"","population":26500,"name":"Rushon District","bfs":"TJ-039","district":"","provider":"unknown","has_mx":false,"reason":"No MX records found"},{"country":"TJ","canton":"Khatlon Province","osm_relation_id":3281940,"domain":"","population":49700,"name":"Sarband District","bfs":"TJ-040","district":"","provider":"unknown","has_mx":false,"reason":"No MX records found"},{"country":"TJ","canton":"Districts under Central Government Jurisdiction","osm_relation_id":3281948,"domain":"","population":121900,"name":"Shahrinaw District","bfs":"TJ-041","district":"","provider":"unknown","has_mx":false,"reason":"No MX records found"},{"country":"TJ","canton":"Sughd Province","osm_relation_id":3280685,"domain":"","population":46200,"name":"Shahristan District","bfs":"TJ-042","district":"","provider":"unknown","has_mx":false,"reason":"No MX records found"},{"country":"TJ","canton":"Khatlon Province","osm_relation_id":6870523,"domain":"","population":57700,"name":"Shamsiddin Shohin District","bfs":"TJ-043","district":"","provider":"unknown","has_mx":false,"reason":"No MX records found"},{"country":"TJ","canton":"Gorno-Badakhshan Autonomous Region","osm_relation_id":3281967,"domain":"","population":39500,"name":"Shughnon District","bfs":"TJ-044","district":"","provider":"unknown","has_mx":false,"reason":"No MX records found"},{"country":"TJ","canton":"Sughd Province","osm_relation_id":3280688,"domain":"spitamen.tj","population":149700,"name":"Spitamen District","bfs":"TJ-045","mx_countries":["TJ"],"district":"","provider":"independent","has_mx":true,"mx":["mail.spitamen.tj","mail.spitamen.tj"],"reason":"MX (mail.spitamen.tj, mail.spitamen.tj) is self-hosted"},{"country":"TJ","canton":"Khatlon Province","osm_relation_id":3281950,"domain":"","population":63800,"name":"Temurmalik District","bfs":"TJ-046","district":"","provider":"unknown","has_mx":false,"reason":"No MX records found"},{"country":"TJ","canton":"Districts under Central Government Jurisdiction","domain":"tojikobod.tj","population":50900,"name":"Tojikobod District","bfs":"TJ-047","mx_countries":["TJ"],"district":"","provider":"independent","has_mx":true,"mx":["mail.tojikobod.tj"],"reason":"MX (mail.tojikobod.tj) is self-hosted"},{"country":"TJ","canton":"Districts under Central Government Jurisdiction","osm_relation_id":3281944,"domain":"tursunzoda.tj","population":320200,"name":"Tursunzoda District","bfs":"TJ-048","mx_countries":["TJ"],"district":"","provider":"independent","has_mx":true,"mx":["mail.tursunzoda.tj"],"reason":"MX (mail.tursunzoda.tj) is self-hosted"},{"country":"TJ","canton":"Tajik Soviet Socialist Republic","osm_relation_id":3281970,"domain":"vahdat.tj","population":324000,"name":"Vahdat District","bfs":"TJ-049","mx_countries":["TJ"],"district":"","provider":"independent","has_mx":true,"mx":["mail.vahdat.tj"],"reason":"MX (mail.vahdat.tj) is self-hosted","autodiscover":{"autodiscover_srv":"cpanelemaildiscovery.cpanel.net"}},{"country":"TJ","canton":"Khatlon Province","osm_relation_id":3281943,"domain":"vakhsh.tj","population":176800,"name":"Vakhsh District","bfs":"TJ-050","mx_countries":["TJ"],"district":"","provider":"independent","has_mx":true,"mx":["mail.vakhsh.tj"],"reason":"MX (mail.vakhsh.tj) is self-hosted"},{"country":"TJ","canton":"Gorno-Badakhshan Autonomous Region","osm_relation_id":3281956,"domain":"","population":34100,"name":"Vanj District","bfs":"TJ-051","district":"","provider":"unknown","has_mx":false,"reason":"No MX records found"},{"country":"TJ","canton":"Tajikistan","osm_relation_id":3281939,"domain":"varzob.tj","population":82200,"name":"Varzob District","bfs":"TJ-052","mx_countries":["TJ"],"district":"","provider":"independent","has_mx":true,"mx":["mail.varzob.tj"],"reason":"MX (mail.varzob.tj) is self-hosted"},{"country":"TJ","canton":"Khatlon Province","osm_relation_id":3281955,"domain":"vose.tj","population":228200,"name":"Vose' District","bfs":"TJ-053","mx_countries":["RU"],"district":"","provider":"independent","has_mx":true,"mx":["emx.mail.ru"],"reason":"MX (emx.mail.ru) is self-hosted","spf":"v=spf1 ip4:185.200.240.65 a mx ~all"},{"country":"TJ","canton":"Khatlon Province","osm_relation_id":3281960,"domain":"yovon.tj","population":210400,"name":"Yovon District","bfs":"TJ-054","mx_countries":["TJ"],"district":"","provider":"independent","has_mx":true,"mx":["mail.yovon.tj"],"reason":"MX (mail.yovon.tj) is self-hosted"},{"country":"TJ","canton":"Sughd Province","osm_relation_id":3280689,"domain":"","population":88200,"name":"Zafarobod District","bfs":"TJ-055","district":"","provider":"unknown","has_mx":false,"reason":"No MX records found"}]